{"status":"ok","message-type":"event-list","message":{"next-cursor":"a438e4eb-2cd4-44d5-ace5-e019931aa292","total-results":69,"items-per-page":1000,"events":[{"license":"https:\/\/creativecommons.org\/publicdomain\/zero\/1.0\/","obj_id":"https:\/\/doi.org\/10.1177\/10778010222183107","source_token":"45a1ef76-4f43-4cdc-9ba8-5a6ad01cc231","occurred_at":"2018-07-12T17:25:55Z","subj_id":"http:\/\/twitter.com\/VAWJournal\/statuses\/1017460057368354817","id":"a216b4d7-9feb-4423-b67a-004968abb39e","evidence_record":"https:\/\/evidence.eventdata.crossref.org\/evidence\/20180712-twitter-cd8fffe4-d13c-4dd1-84c5-505bff8ac033","terms":"https:\/\/doi.org\/10.13003\/CED-terms-of-use","action":"add","subj":{"pid":"http:\/\/twitter.com\/VAWJournal\/statuses\/1017460057368354817","url":"http:\/\/twitter.com\/VAWJournal\/statuses\/1017460057368354817","title":"Tweet 1017460057368354817","issued":"2018-07-12T17:25:55.000Z","author":{"url":"http:\/\/www.twitter.com\/VAWJournal"},"original-tweet-url":"http:\/\/twitter.com\/VAWJournal\/statuses\/1017460057368354817","original-tweet-author":null,"alternative-id":"1017460057368354817"},"source_id":"twitter","obj":{"pid":"https:\/\/doi.org\/10.1177\/10778010222183107","url":"http:\/\/journals.sagepub.com\/doi\/abs\/10.1177\/10778010222183107"},"timestamp":"2018-07-12T17:26:58Z","relation_type_id":"discusses"},{"license":"https:\/\/creativecommons.org\/publicdomain\/zero\/1.0\/","obj_id":"https:\/\/doi.org\/10.1177\/10778010222183107","source_token":"45a1ef76-4f43-4cdc-9ba8-5a6ad01cc231","occurred_at":"2018-07-12T20:20:14Z","subj_id":"http:\/\/twitter.com\/doc_ebp\/statuses\/1017503923308056578","id":"5af8ebfa-211b-4d46-8f22-5077d8e4693a","evidence_record":"https:\/\/evidence.eventdata.crossref.org\/evidence\/20180712-twitter-95686603-3572-4571-92f1-b21ee64b96b1","terms":"https:\/\/doi.org\/10.13003\/CED-terms-of-use","action":"add","subj":{"pid":"http:\/\/twitter.com\/doc_ebp\/statuses\/1017503923308056578","url":"http:\/\/twitter.com\/doc_ebp\/statuses\/1017503923308056578","title":"Tweet 1017503923308056578","issued":"2018-07-12T20:20:14.000Z","author":{"url":"http:\/\/www.twitter.com\/doc_ebp"},"original-tweet-url":"http:\/\/twitter.com\/VAWJournal\/statuses\/1017460057368354817","original-tweet-author":"http:\/\/www.twitter.com\/VAWJournal","alternative-id":"1017503923308056578"},"source_id":"twitter","obj":{"pid":"https:\/\/doi.org\/10.1177\/10778010222183107","url":"http:\/\/journals.sagepub.com\/doi\/abs\/10.1177\/10778010222183107"},"timestamp":"2018-07-12T20:21:54Z","relation_type_id":"discusses"},{"license":"https:\/\/creativecommons.org\/publicdomain\/zero\/1.0\/","obj_id":"https:\/\/doi.org\/10.1177\/10778010222183107","source_token":"45a1ef76-4f43-4cdc-9ba8-5a6ad01cc231","occurred_at":"2018-07-14T21:30:03Z","subj_id":"http:\/\/twitter.com\/EstherCalvete\/statuses\/1018246270044049409","id":"c5cfa9c6-91ef-4993-be91-64cb969bf322","evidence_record":"https:\/\/evidence.eventdata.crossref.org\/evidence\/20180714-twitter-b31d23dc-dfe6-4fc5-9453-9d0a2e208690","terms":"https:\/\/doi.org\/10.13003\/CED-terms-of-use","action":"add","subj":{"pid":"http:\/\/twitter.com\/EstherCalvete\/statuses\/1018246270044049409","url":"http:\/\/twitter.com\/EstherCalvete\/statuses\/1018246270044049409","title":"Tweet 1018246270044049409","issued":"2018-07-14T21:30:03.000Z","author":{"url":"http:\/\/www.twitter.com\/EstherCalvete"},"original-tweet-url":"http:\/\/twitter.com\/VAWJournal\/statuses\/1017460057368354817","original-tweet-author":"http:\/\/www.twitter.com\/VAWJournal","alternative-id":"1018246270044049409"},"source_id":"twitter","obj":{"pid":"https:\/\/doi.org\/10.1177\/10778010222183107","url":"http:\/\/journals.sagepub.com\/doi\/abs\/10.1177\/10778010222183107"},"timestamp":"2018-07-14T21:31:02Z","relation_type_id":"discusses"},{"license":"https:\/\/creativecommons.org\/publicdomain\/zero\/1.0\/","obj_id":"https:\/\/doi.org\/10.1177\/10778010222183107","source_token":"45a1ef76-4f43-4cdc-9ba8-5a6ad01cc231","occurred_at":"2018-07-15T19:56:05Z","subj_id":"http:\/\/twitter.com\/marisaespinaf\/statuses\/1018585008372580353","id":"835b1acf-268e-4902-bc4d-187e8c02a361","evidence_record":"https:\/\/evidence.eventdata.crossref.org\/evidence\/20180715-twitter-79061dbf-92ce-4eb8-865f-a8fade26607a","terms":"https:\/\/doi.org\/10.13003\/CED-terms-of-use","action":"add","subj":{"pid":"http:\/\/twitter.com\/marisaespinaf\/statuses\/1018585008372580353","url":"http:\/\/twitter.com\/marisaespinaf\/statuses\/1018585008372580353","title":"Tweet 1018585008372580353","issued":"2018-07-15T19:56:05.000Z","author":{"url":"http:\/\/www.twitter.com\/marisaespinaf"},"original-tweet-url":"http:\/\/twitter.com\/VAWJournal\/statuses\/1017460057368354817","original-tweet-author":"http:\/\/www.twitter.com\/VAWJournal","alternative-id":"1018585008372580353"},"source_id":"twitter","obj":{"pid":"https:\/\/doi.org\/10.1177\/10778010222183107","url":"http:\/\/journals.sagepub.com\/doi\/abs\/10.1177\/10778010222183107"},"timestamp":"2018-07-15T19:56:44Z","relation_type_id":"discusses"},{"license":"https:\/\/creativecommons.org\/publicdomain\/zero\/1.0\/","obj_id":"https:\/\/doi.org\/10.1177\/10778010222183107","source_token":"36c35e23-8757-4a9d-aacf-345e9b7eb50d","occurred_at":"2018-07-30T22:17:36Z","subj_id":"https:\/\/en.wikipedia.org\/api\/rest_v1\/page\/html\/Anita_Raj_(academic)\/852717884","id":"0c804014-4aa4-47a7-875a-e5a987ff5534","evidence_record":"https:\/\/evidence.eventdata.crossref.org\/evidence\/20180730-wikipedia-ee77a1fc-957f-4974-bb25-e934a58f47c5","terms":"https:\/\/doi.org\/10.13003\/CED-terms-of-use","action":"add","subj":{"pid":"https:\/\/en.wikipedia.org\/wiki\/Anita_Raj_(academic)","url":"https:\/\/en.wikipedia.org\/w\/index.php?title=Anita_Raj_(academic)&oldid=852717884","title":"Anita Raj (academic)","work_type_id":"entry-encyclopedia","api-url":"https:\/\/en.wikipedia.org\/api\/rest_v1\/page\/html\/Anita_Raj_(academic)\/852717884"},"source_id":"wikipedia","obj":{"pid":"https:\/\/doi.org\/10.1177\/10778010222183107","url":"http:\/\/journals.sagepub.com\/doi\/pdf\/10.1177\/10778010222183107"},"timestamp":"2018-07-30T22:18:46Z","relation_type_id":"references"},{"license":"https:\/\/creativecommons.org\/publicdomain\/zero\/1.0\/","obj_id":"https:\/\/doi.org\/10.1177\/10778010222183107","source_token":"36c35e23-8757-4a9d-aacf-345e9b7eb50d","occurred_at":"2018-07-30T22:18:33Z","subj_id":"https:\/\/en.wikipedia.org\/api\/rest_v1\/page\/html\/Anita_Raj_(academic)\/852717983","id":"1ebc65be-5225-485d-aaa2-870a4ed88be1","evidence_record":"https:\/\/evidence.eventdata.crossref.org\/evidence\/20180730-wikipedia-d954b875-c013-4bcf-98f9-26ea82a36509","terms":"https:\/\/doi.org\/10.13003\/CED-terms-of-use","action":"add","subj":{"pid":"https:\/\/en.wikipedia.org\/wiki\/Anita_Raj_(academic)","url":"https:\/\/en.wikipedia.org\/w\/index.php?title=Anita_Raj_(academic)&oldid=852717983","title":"Anita Raj (academic)","work_type_id":"entry-encyclopedia","api-url":"https:\/\/en.wikipedia.org\/api\/rest_v1\/page\/html\/Anita_Raj_(academic)\/852717983"},"source_id":"wikipedia","obj":{"pid":"https:\/\/doi.org\/10.1177\/10778010222183107","url":"http:\/\/journals.sagepub.com\/doi\/pdf\/10.1177\/10778010222183107"},"timestamp":"2018-07-30T22:20:01Z","relation_type_id":"references"},{"license":"https:\/\/creativecommons.org\/publicdomain\/zero\/1.0\/","obj_id":"https:\/\/doi.org\/10.1177\/10778010222183107","source_token":"36c35e23-8757-4a9d-aacf-345e9b7eb50d","occurred_at":"2018-07-30T22:19:09Z","subj_id":"https:\/\/en.wikipedia.org\/api\/rest_v1\/page\/html\/Anita_Raj_(academic)\/852718056","id":"65aeaf05-2ee0-4de0-a416-bc26dfdfe5f8","evidence_record":"https:\/\/evidence.eventdata.crossref.org\/evidence\/20180730-wikipedia-118f31a3-4f9e-459d-940e-2a57f5369269","terms":"https:\/\/doi.org\/10.13003\/CED-terms-of-use","action":"add","subj":{"pid":"https:\/\/en.wikipedia.org\/wiki\/Anita_Raj_(academic)","url":"https:\/\/en.wikipedia.org\/w\/index.php?title=Anita_Raj_(academic)&oldid=852718056","title":"Anita Raj (academic)","work_type_id":"entry-encyclopedia","api-url":"https:\/\/en.wikipedia.org\/api\/rest_v1\/page\/html\/Anita_Raj_(academic)\/852718056"},"source_id":"wikipedia","obj":{"pid":"https:\/\/doi.org\/10.1177\/10778010222183107","url":"http:\/\/journals.sagepub.com\/doi\/pdf\/10.1177\/10778010222183107"},"timestamp":"2018-07-30T22:21:35Z","relation_type_id":"references"},{"license":"https:\/\/creativecommons.org\/publicdomain\/zero\/1.0\/","obj_id":"https:\/\/doi.org\/10.1177\/10778010222183107","source_token":"36c35e23-8757-4a9d-aacf-345e9b7eb50d","occurred_at":"2018-07-30T22:19:45Z","subj_id":"https:\/\/en.wikipedia.org\/api\/rest_v1\/page\/html\/Anita_Raj_(academic)\/852718121","id":"dc529363-2453-490d-abe1-9cd83e55ee3a","evidence_record":"https:\/\/evidence.eventdata.crossref.org\/evidence\/20180730-wikipedia-2e0d6e8c-d192-430c-93ad-67caebf3d417","terms":"https:\/\/doi.org\/10.13003\/CED-terms-of-use","action":"add","subj":{"pid":"https:\/\/en.wikipedia.org\/wiki\/Anita_Raj_(academic)","url":"https:\/\/en.wikipedia.org\/w\/index.php?title=Anita_Raj_(academic)&oldid=852718121","title":"Anita Raj (academic)","work_type_id":"entry-encyclopedia","api-url":"https:\/\/en.wikipedia.org\/api\/rest_v1\/page\/html\/Anita_Raj_(academic)\/852718121"},"source_id":"wikipedia","obj":{"pid":"https:\/\/doi.org\/10.1177\/10778010222183107","url":"http:\/\/journals.sagepub.com\/doi\/pdf\/10.1177\/10778010222183107"},"timestamp":"2018-07-30T22:21:55Z","relation_type_id":"references"},{"license":"https:\/\/creativecommons.org\/publicdomain\/zero\/1.0\/","obj_id":"https:\/\/doi.org\/10.1177\/10778010222183107","source_token":"36c35e23-8757-4a9d-aacf-345e9b7eb50d","occurred_at":"2018-07-30T22:20:46Z","subj_id":"https:\/\/en.wikipedia.org\/api\/rest_v1\/page\/html\/Anita_Raj_(academic)\/852718255","id":"a6e10e92-065d-4902-aa8f-f7996184de47","evidence_record":"https:\/\/evidence.eventdata.crossref.org\/evidence\/20180730-wikipedia-6e7e278c-9757-4cd6-b90a-dc0dc83efa94","terms":"https:\/\/doi.org\/10.13003\/CED-terms-of-use","action":"add","subj":{"pid":"https:\/\/en.wikipedia.org\/wiki\/Anita_Raj_(academic)","url":"https:\/\/en.wikipedia.org\/w\/index.php?title=Anita_Raj_(academic)&oldid=852718255","title":"Anita Raj (academic)","work_type_id":"entry-encyclopedia","api-url":"https:\/\/en.wikipedia.org\/api\/rest_v1\/page\/html\/Anita_Raj_(academic)\/852718255"},"source_id":"wikipedia","obj":{"pid":"https:\/\/doi.org\/10.1177\/10778010222183107","url":"http:\/\/journals.sagepub.com\/doi\/pdf\/10.1177\/10778010222183107"},"timestamp":"2018-07-30T22:22:12Z","relation_type_id":"references"},{"license":"https:\/\/creativecommons.org\/publicdomain\/zero\/1.0\/","obj_id":"https:\/\/doi.org\/10.1177\/10778010222183107","source_token":"36c35e23-8757-4a9d-aacf-345e9b7eb50d","occurred_at":"2018-07-30T22:22:34Z","subj_id":"https:\/\/en.wikipedia.org\/api\/rest_v1\/page\/html\/Anita_Raj_(academic)\/852718464","id":"baccb5ab-c1f8-4734-bcb0-3f39a21d142d","evidence_record":"https:\/\/evidence.eventdata.crossref.org\/evidence\/20180730-wikipedia-c5040a20-dc37-45c6-8615-cd3081cc40fb","terms":"https:\/\/doi.org\/10.13003\/CED-terms-of-use","action":"add","subj":{"pid":"https:\/\/en.wikipedia.org\/wiki\/Anita_Raj_(academic)","url":"https:\/\/en.wikipedia.org\/w\/index.php?title=Anita_Raj_(academic)&oldid=852718464","title":"Anita Raj (academic)","work_type_id":"entry-encyclopedia","api-url":"https:\/\/en.wikipedia.org\/api\/rest_v1\/page\/html\/Anita_Raj_(academic)\/852718464"},"source_id":"wikipedia","obj":{"pid":"https:\/\/doi.org\/10.1177\/10778010222183107","url":"http:\/\/journals.sagepub.com\/doi\/pdf\/10.1177\/10778010222183107"},"timestamp":"2018-07-30T22:23:31Z","relation_type_id":"references"},{"license":"https:\/\/creativecommons.org\/publicdomain\/zero\/1.0\/","obj_id":"https:\/\/doi.org\/10.1177\/10778010222183107","source_token":"36c35e23-8757-4a9d-aacf-345e9b7eb50d","occurred_at":"2018-07-30T22:21:45Z","subj_id":"https:\/\/en.wikipedia.org\/api\/rest_v1\/page\/html\/Anita_Raj_(academic)\/852718366","id":"b7e8d830-fb72-4e1a-a791-ef438e3125d5","evidence_record":"https:\/\/evidence.eventdata.crossref.org\/evidence\/20180730-wikipedia-e86fbc83-9177-41de-903f-f73fb609c9b6","terms":"https:\/\/doi.org\/10.13003\/CED-terms-of-use","action":"add","subj":{"pid":"https:\/\/en.wikipedia.org\/wiki\/Anita_Raj_(academic)","url":"https:\/\/en.wikipedia.org\/w\/index.php?title=Anita_Raj_(academic)&oldid=852718366","title":"Anita Raj (academic)","work_type_id":"entry-encyclopedia","api-url":"https:\/\/en.wikipedia.org\/api\/rest_v1\/page\/html\/Anita_Raj_(academic)\/852718366"},"source_id":"wikipedia","obj":{"pid":"https:\/\/doi.org\/10.1177\/10778010222183107","url":"http:\/\/journals.sagepub.com\/doi\/pdf\/10.1177\/10778010222183107"},"timestamp":"2018-07-30T22:23:55Z","relation_type_id":"references"},{"license":"https:\/\/creativecommons.org\/publicdomain\/zero\/1.0\/","obj_id":"https:\/\/doi.org\/10.1177\/10778010222183107","source_token":"36c35e23-8757-4a9d-aacf-345e9b7eb50d","occurred_at":"2018-07-30T22:23:46Z","subj_id":"https:\/\/en.wikipedia.org\/api\/rest_v1\/page\/html\/Anita_Raj_(academic)\/852718605","id":"3967c8ca-4115-4cb5-bca5-2fd249c388f8","evidence_record":"https:\/\/evidence.eventdata.crossref.org\/evidence\/20180730-wikipedia-0b7e0bf3-58c6-4e47-8a09-6d2bf7fc81fe","terms":"https:\/\/doi.org\/10.13003\/CED-terms-of-use","action":"add","subj":{"pid":"https:\/\/en.wikipedia.org\/wiki\/Anita_Raj_(academic)","url":"https:\/\/en.wikipedia.org\/w\/index.php?title=Anita_Raj_(academic)&oldid=852718605","title":"Anita Raj (academic)","work_type_id":"entry-encyclopedia","api-url":"https:\/\/en.wikipedia.org\/api\/rest_v1\/page\/html\/Anita_Raj_(academic)\/852718605"},"source_id":"wikipedia","obj":{"pid":"https:\/\/doi.org\/10.1177\/10778010222183107","url":"http:\/\/journals.sagepub.com\/doi\/pdf\/10.1177\/10778010222183107"},"timestamp":"2018-07-30T22:24:28Z","relation_type_id":"references"},{"license":"https:\/\/creativecommons.org\/publicdomain\/zero\/1.0\/","obj_id":"https:\/\/doi.org\/10.1177\/10778010222183107","source_token":"36c35e23-8757-4a9d-aacf-345e9b7eb50d","occurred_at":"2018-07-30T22:23:27Z","subj_id":"https:\/\/en.wikipedia.org\/api\/rest_v1\/page\/html\/Anita_Raj_(academic)\/852718568","id":"60a45a90-00be-41de-bb99-4bfca532dd2a","evidence_record":"https:\/\/evidence.eventdata.crossref.org\/evidence\/20180730-wikipedia-289e36a7-4619-44f7-8dc7-f0e83e7c87e8","terms":"https:\/\/doi.org\/10.13003\/CED-terms-of-use","action":"add","subj":{"pid":"https:\/\/en.wikipedia.org\/wiki\/Anita_Raj_(academic)","url":"https:\/\/en.wikipedia.org\/w\/index.php?title=Anita_Raj_(academic)&oldid=852718568","title":"Anita Raj (academic)","work_type_id":"entry-encyclopedia","api-url":"https:\/\/en.wikipedia.org\/api\/rest_v1\/page\/html\/Anita_Raj_(academic)\/852718568"},"source_id":"wikipedia","obj":{"pid":"https:\/\/doi.org\/10.1177\/10778010222183107","url":"http:\/\/journals.sagepub.com\/doi\/pdf\/10.1177\/10778010222183107"},"timestamp":"2018-07-30T22:25:09Z","relation_type_id":"references"},{"license":"https:\/\/creativecommons.org\/publicdomain\/zero\/1.0\/","obj_id":"https:\/\/doi.org\/10.1177\/10778010222183107","source_token":"36c35e23-8757-4a9d-aacf-345e9b7eb50d","occurred_at":"2018-07-30T22:24:25Z","subj_id":"https:\/\/en.wikipedia.org\/api\/rest_v1\/page\/html\/Anita_Raj_(academic)\/852718681","id":"5d46bb34-8c2d-42aa-8f07-2d3e2b6e38b8","evidence_record":"https:\/\/evidence.eventdata.crossref.org\/evidence\/20180730-wikipedia-dc504e51-7a7c-4664-885b-cba46e64cba4","terms":"https:\/\/doi.org\/10.13003\/CED-terms-of-use","action":"add","subj":{"pid":"https:\/\/en.wikipedia.org\/wiki\/Anita_Raj_(academic)","url":"https:\/\/en.wikipedia.org\/w\/index.php?title=Anita_Raj_(academic)&oldid=852718681","title":"Anita Raj (academic)","work_type_id":"entry-encyclopedia","api-url":"https:\/\/en.wikipedia.org\/api\/rest_v1\/page\/html\/Anita_Raj_(academic)\/852718681"},"source_id":"wikipedia","obj":{"pid":"https:\/\/doi.org\/10.1177\/10778010222183107","url":"http:\/\/journals.sagepub.com\/doi\/pdf\/10.1177\/10778010222183107"},"timestamp":"2018-07-30T22:25:40Z","relation_type_id":"references"},{"license":"https:\/\/creativecommons.org\/publicdomain\/zero\/1.0\/","obj_id":"https:\/\/doi.org\/10.1177\/10778010222183107","source_token":"36c35e23-8757-4a9d-aacf-345e9b7eb50d","occurred_at":"2018-07-30T22:41:03Z","subj_id":"https:\/\/en.wikipedia.org\/api\/rest_v1\/page\/html\/Anita_Raj_(academic)\/852720458","id":"2414133a-188a-4857-a341-0f9dba6dca21","evidence_record":"https:\/\/evidence.eventdata.crossref.org\/evidence\/20180730-wikipedia-62b49d75-5ae8-4e82-a913-2eee75f780bc","terms":"https:\/\/doi.org\/10.13003\/CED-terms-of-use","action":"add","subj":{"pid":"https:\/\/en.wikipedia.org\/wiki\/Anita_Raj_(academic)","url":"https:\/\/en.wikipedia.org\/w\/index.php?title=Anita_Raj_(academic)&oldid=852720458","title":"Anita Raj (academic)","work_type_id":"entry-encyclopedia","api-url":"https:\/\/en.wikipedia.org\/api\/rest_v1\/page\/html\/Anita_Raj_(academic)\/852720458"},"source_id":"wikipedia","obj":{"pid":"https:\/\/doi.org\/10.1177\/10778010222183107","url":"http:\/\/journals.sagepub.com\/doi\/pdf\/10.1177\/10778010222183107"},"timestamp":"2018-07-30T22:42:22Z","relation_type_id":"references"},{"license":"https:\/\/creativecommons.org\/publicdomain\/zero\/1.0\/","obj_id":"https:\/\/doi.org\/10.1177\/10778010222183107","source_token":"36c35e23-8757-4a9d-aacf-345e9b7eb50d","occurred_at":"2018-07-31T00:43:02Z","subj_id":"https:\/\/en.wikipedia.org\/api\/rest_v1\/page\/html\/Anita_Raj_(academic)\/852733646","id":"a61c54eb-c24a-444a-80f6-c7714c5635b3","evidence_record":"https:\/\/evidence.eventdata.crossref.org\/evidence\/20180731-wikipedia-8cd3e062-4062-4c0e-acd1-7d55955e6562","terms":"https:\/\/doi.org\/10.13003\/CED-terms-of-use","action":"add","subj":{"pid":"https:\/\/en.wikipedia.org\/wiki\/Anita_Raj_(academic)","url":"https:\/\/en.wikipedia.org\/w\/index.php?title=Anita_Raj_(academic)&oldid=852733646","title":"Anita Raj (academic)","work_type_id":"entry-encyclopedia","api-url":"https:\/\/en.wikipedia.org\/api\/rest_v1\/page\/html\/Anita_Raj_(academic)\/852733646"},"source_id":"wikipedia","obj":{"pid":"https:\/\/doi.org\/10.1177\/10778010222183107","url":"http:\/\/journals.sagepub.com\/doi\/pdf\/10.1177\/10778010222183107"},"timestamp":"2018-07-31T00:44:36Z","relation_type_id":"references"},{"license":"https:\/\/creativecommons.org\/publicdomain\/zero\/1.0\/","obj_id":"https:\/\/doi.org\/10.1177\/10778010222183107","source_token":"36c35e23-8757-4a9d-aacf-345e9b7eb50d","occurred_at":"2018-08-01T10:01:19Z","subj_id":"https:\/\/en.wikipedia.org\/api\/rest_v1\/page\/html\/Anita_Raj_(academic)\/852933297","id":"777a0574-85ce-4468-99d2-93c105cd8f90","evidence_record":"https:\/\/evidence.eventdata.crossref.org\/evidence\/20180801-wikipedia-0e5bc082-2cef-461d-b31c-fb2cbd0674db","terms":"https:\/\/doi.org\/10.13003\/CED-terms-of-use","action":"add","subj":{"pid":"https:\/\/en.wikipedia.org\/wiki\/Anita_Raj_(academic)","url":"https:\/\/en.wikipedia.org\/w\/index.php?title=Anita_Raj_(academic)&oldid=852933297","title":"Anita Raj (academic)","work_type_id":"entry-encyclopedia","api-url":"https:\/\/en.wikipedia.org\/api\/rest_v1\/page\/html\/Anita_Raj_(academic)\/852933297"},"source_id":"wikipedia","obj":{"pid":"https:\/\/doi.org\/10.1177\/10778010222183107","url":"http:\/\/journals.sagepub.com\/doi\/pdf\/10.1177\/10778010222183107"},"timestamp":"2018-08-01T10:03:15Z","relation_type_id":"references"},{"license":"https:\/\/creativecommons.org\/publicdomain\/zero\/1.0\/","obj_id":"https:\/\/doi.org\/10.1177\/10778010222183107","source_token":"36c35e23-8757-4a9d-aacf-345e9b7eb50d","occurred_at":"2018-08-01T16:34:35Z","subj_id":"https:\/\/en.wikipedia.org\/api\/rest_v1\/page\/html\/Anita_Raj_(academic)\/852978456","id":"a8312a54-b7aa-4ba8-90f3-94d72a0911e3","evidence_record":"https:\/\/evidence.eventdata.crossref.org\/evidence\/20180801-wikipedia-a31f7771-1fa0-4ab3-b3e3-949847ae986f","terms":"https:\/\/doi.org\/10.13003\/CED-terms-of-use","action":"add","subj":{"pid":"https:\/\/en.wikipedia.org\/wiki\/Anita_Raj_(academic)","url":"https:\/\/en.wikipedia.org\/w\/index.php?title=Anita_Raj_(academic)&oldid=852978456","title":"Anita Raj (academic)","work_type_id":"entry-encyclopedia","api-url":"https:\/\/en.wikipedia.org\/api\/rest_v1\/page\/html\/Anita_Raj_(academic)\/852978456"},"source_id":"wikipedia","obj":{"pid":"https:\/\/doi.org\/10.1177\/10778010222183107","url":"http:\/\/journals.sagepub.com\/doi\/pdf\/10.1177\/10778010222183107"},"timestamp":"2018-08-01T16:36:00Z","relation_type_id":"references"},{"license":"https:\/\/creativecommons.org\/publicdomain\/zero\/1.0\/","obj_id":"https:\/\/doi.org\/10.1177\/10778010222183107","source_token":"36c35e23-8757-4a9d-aacf-345e9b7eb50d","occurred_at":"2018-08-01T17:43:29Z","subj_id":"https:\/\/en.wikipedia.org\/api\/rest_v1\/page\/html\/Anita_Raj_(academic)\/852987376","id":"e04df0da-3c6c-4cbe-8ac3-d66550b088a8","evidence_record":"https:\/\/evidence.eventdata.crossref.org\/evidence\/20180801-wikipedia-0112a483-2377-4196-be24-aa9497630c92","terms":"https:\/\/doi.org\/10.13003\/CED-terms-of-use","action":"add","subj":{"pid":"https:\/\/en.wikipedia.org\/wiki\/Anita_Raj_(academic)","url":"https:\/\/en.wikipedia.org\/w\/index.php?title=Anita_Raj_(academic)&oldid=852987376","title":"Anita Raj (academic)","work_type_id":"entry-encyclopedia","api-url":"https:\/\/en.wikipedia.org\/api\/rest_v1\/page\/html\/Anita_Raj_(academic)\/852987376"},"source_id":"wikipedia","obj":{"pid":"https:\/\/doi.org\/10.1177\/10778010222183107","url":"http:\/\/journals.sagepub.com\/doi\/pdf\/10.1177\/10778010222183107"},"timestamp":"2018-08-01T17:44:46Z","relation_type_id":"references"},{"license":"https:\/\/creativecommons.org\/publicdomain\/zero\/1.0\/","obj_id":"https:\/\/doi.org\/10.1177\/10778010222183107","source_token":"36c35e23-8757-4a9d-aacf-345e9b7eb50d","occurred_at":"2018-08-01T17:46:11Z","subj_id":"https:\/\/en.wikipedia.org\/api\/rest_v1\/page\/html\/Anita_Raj_(academic)\/852987713","id":"752874fe-62b7-4505-a240-616ef7382107","evidence_record":"https:\/\/evidence.eventdata.crossref.org\/evidence\/20180801-wikipedia-d75ed240-e040-4e3f-bb4a-7b56835c119d","terms":"https:\/\/doi.org\/10.13003\/CED-terms-of-use","action":"add","subj":{"pid":"https:\/\/en.wikipedia.org\/wiki\/Anita_Raj_(academic)","url":"https:\/\/en.wikipedia.org\/w\/index.php?title=Anita_Raj_(academic)&oldid=852987713","title":"Anita Raj (academic)","work_type_id":"entry-encyclopedia","api-url":"https:\/\/en.wikipedia.org\/api\/rest_v1\/page\/html\/Anita_Raj_(academic)\/852987713"},"source_id":"wikipedia","obj":{"pid":"https:\/\/doi.org\/10.1177\/10778010222183107","url":"http:\/\/journals.sagepub.com\/doi\/pdf\/10.1177\/10778010222183107"},"timestamp":"2018-08-01T17:47:07Z","relation_type_id":"references"},{"license":"https:\/\/creativecommons.org\/publicdomain\/zero\/1.0\/","obj_id":"https:\/\/doi.org\/10.1177\/10778010222183107","source_token":"36c35e23-8757-4a9d-aacf-345e9b7eb50d","occurred_at":"2018-08-03T06:32:05Z","subj_id":"https:\/\/en.wikipedia.org\/api\/rest_v1\/page\/html\/Anita_Raj_(academic)\/853220176","id":"416535af-ba04-435d-af0e-23140b745f34","evidence_record":"https:\/\/evidence.eventdata.crossref.org\/evidence\/20180803-wikipedia-ab878b75-0d88-418e-96e7-3941acbbb916","terms":"https:\/\/doi.org\/10.13003\/CED-terms-of-use","action":"add","subj":{"pid":"https:\/\/en.wikipedia.org\/wiki\/Anita_Raj_(academic)","url":"https:\/\/en.wikipedia.org\/w\/index.php?title=Anita_Raj_(academic)&oldid=853220176","title":"Anita Raj (academic)","work_type_id":"entry-encyclopedia","api-url":"https:\/\/en.wikipedia.org\/api\/rest_v1\/page\/html\/Anita_Raj_(academic)\/853220176"},"source_id":"wikipedia","obj":{"pid":"https:\/\/doi.org\/10.1177\/10778010222183107","url":"http:\/\/journals.sagepub.com\/doi\/pdf\/10.1177\/10778010222183107"},"timestamp":"2018-08-03T06:33:57Z","relation_type_id":"references"},{"license":"https:\/\/creativecommons.org\/publicdomain\/zero\/1.0\/","obj_id":"https:\/\/doi.org\/10.1177\/10778010222183107","source_token":"36c35e23-8757-4a9d-aacf-345e9b7eb50d","occurred_at":"2018-08-04T07:07:41Z","subj_id":"https:\/\/en.wikipedia.org\/api\/rest_v1\/page\/html\/Anita_Raj_(academic)\/853363795","id":"ee1d9e08-e7e1-417f-a4b1-1beca5d8512c","evidence_record":"https:\/\/evidence.eventdata.crossref.org\/evidence\/20180804-wikipedia-a30d3545-9039-48ca-958b-f15ecda3ebb2","terms":"https:\/\/doi.org\/10.13003\/CED-terms-of-use","action":"add","subj":{"pid":"https:\/\/en.wikipedia.org\/wiki\/Anita_Raj_(academic)","url":"https:\/\/en.wikipedia.org\/w\/index.php?title=Anita_Raj_(academic)&oldid=853363795","title":"Anita Raj (academic)","work_type_id":"entry-encyclopedia","api-url":"https:\/\/en.wikipedia.org\/api\/rest_v1\/page\/html\/Anita_Raj_(academic)\/853363795"},"source_id":"wikipedia","obj":{"pid":"https:\/\/doi.org\/10.1177\/10778010222183107","url":"http:\/\/journals.sagepub.com\/doi\/pdf\/10.1177\/10778010222183107"},"timestamp":"2018-08-04T07:09:38Z","relation_type_id":"references"},{"license":"https:\/\/creativecommons.org\/publicdomain\/zero\/1.0\/","obj_id":"https:\/\/doi.org\/10.1177\/10778010222183107","source_token":"36c35e23-8757-4a9d-aacf-345e9b7eb50d","occurred_at":"2018-08-06T23:24:32Z","subj_id":"https:\/\/en.wikipedia.org\/api\/rest_v1\/page\/html\/Anita_Raj_(academic)\/853781493","id":"c51a351f-ac92-40ff-b4c3-32b3b7c52d41","evidence_record":"https:\/\/evidence.eventdata.crossref.org\/evidence\/20180806-wikipedia-a11bb90f-a2e8-4de0-9479-9a311332e6f4","terms":"https:\/\/doi.org\/10.13003\/CED-terms-of-use","action":"add","subj":{"pid":"https:\/\/en.wikipedia.org\/wiki\/Anita_Raj_(academic)","url":"https:\/\/en.wikipedia.org\/w\/index.php?title=Anita_Raj_(academic)&oldid=853781493","title":"Anita Raj (academic)","work_type_id":"entry-encyclopedia","api-url":"https:\/\/en.wikipedia.org\/api\/rest_v1\/page\/html\/Anita_Raj_(academic)\/853781493"},"source_id":"wikipedia","obj":{"pid":"https:\/\/doi.org\/10.1177\/10778010222183107","url":"http:\/\/journals.sagepub.com\/doi\/pdf\/10.1177\/10778010222183107"},"timestamp":"2018-08-06T23:25:58Z","relation_type_id":"references"},{"license":"https:\/\/creativecommons.org\/publicdomain\/zero\/1.0\/","obj_id":"https:\/\/doi.org\/10.1177\/10778010222183107","source_token":"36c35e23-8757-4a9d-aacf-345e9b7eb50d","occurred_at":"2018-08-06T23:30:18Z","subj_id":"https:\/\/en.wikipedia.org\/api\/rest_v1\/page\/html\/Anita_Raj_(academic)\/853782235","id":"0406afba-df9d-4d1c-8dee-e52b388aae08","evidence_record":"https:\/\/evidence.eventdata.crossref.org\/evidence\/20180806-wikipedia-4822cb8a-b078-444e-9cbb-d3cdc2978561","terms":"https:\/\/doi.org\/10.13003\/CED-terms-of-use","action":"add","subj":{"pid":"https:\/\/en.wikipedia.org\/wiki\/Anita_Raj_(academic)","url":"https:\/\/en.wikipedia.org\/w\/index.php?title=Anita_Raj_(academic)&oldid=853782235","title":"Anita Raj (academic)","work_type_id":"entry-encyclopedia","api-url":"https:\/\/en.wikipedia.org\/api\/rest_v1\/page\/html\/Anita_Raj_(academic)\/853782235"},"source_id":"wikipedia","obj":{"pid":"https:\/\/doi.org\/10.1177\/10778010222183107","url":"http:\/\/journals.sagepub.com\/doi\/pdf\/10.1177\/10778010222183107"},"timestamp":"2018-08-06T23:31:06Z","relation_type_id":"references"},{"license":"https:\/\/creativecommons.org\/publicdomain\/zero\/1.0\/","obj_id":"https:\/\/doi.org\/10.1177\/10778010222183107","source_token":"36c35e23-8757-4a9d-aacf-345e9b7eb50d","occurred_at":"2018-08-07T09:23:21Z","subj_id":"https:\/\/en.wikipedia.org\/api\/rest_v1\/page\/html\/Anita_Raj_(academic)\/853845256","id":"aabd8f15-6dca-4dd6-9c8a-e8e6f5c6ffca","evidence_record":"https:\/\/evidence.eventdata.crossref.org\/evidence\/20180807-wikipedia-648ef99d-a776-4520-ae15-bd45648613ba","terms":"https:\/\/doi.org\/10.13003\/CED-terms-of-use","action":"add","subj":{"pid":"https:\/\/en.wikipedia.org\/wiki\/Anita_Raj_(academic)","url":"https:\/\/en.wikipedia.org\/w\/index.php?title=Anita_Raj_(academic)&oldid=853845256","title":"Anita Raj (academic)","work_type_id":"entry-encyclopedia","api-url":"https:\/\/en.wikipedia.org\/api\/rest_v1\/page\/html\/Anita_Raj_(academic)\/853845256"},"source_id":"wikipedia","obj":{"pid":"https:\/\/doi.org\/10.1177\/10778010222183107","url":"http:\/\/journals.sagepub.com\/doi\/pdf\/10.1177\/10778010222183107"},"timestamp":"2018-08-07T09:24:11Z","relation_type_id":"references"},{"license":"https:\/\/creativecommons.org\/publicdomain\/zero\/1.0\/","obj_id":"https:\/\/doi.org\/10.1177\/10778010222183107","source_token":"36c35e23-8757-4a9d-aacf-345e9b7eb50d","occurred_at":"2018-08-09T12:52:13Z","subj_id":"https:\/\/en.wikipedia.org\/api\/rest_v1\/page\/html\/Anita_Raj_(academic)\/854171405","id":"ab960582-cc17-46f1-86e2-47785fc2922e","evidence_record":"https:\/\/evidence.eventdata.crossref.org\/evidence\/20180809-wikipedia-9e45b76a-7dcd-405e-b388-a6ebffb7d49d","terms":"https:\/\/doi.org\/10.13003\/CED-terms-of-use","action":"add","subj":{"pid":"https:\/\/en.wikipedia.org\/wiki\/Anita_Raj_(academic)","url":"https:\/\/en.wikipedia.org\/w\/index.php?title=Anita_Raj_(academic)&oldid=854171405","title":"Anita Raj (academic)","work_type_id":"entry-encyclopedia","api-url":"https:\/\/en.wikipedia.org\/api\/rest_v1\/page\/html\/Anita_Raj_(academic)\/854171405"},"source_id":"wikipedia","obj":{"pid":"https:\/\/doi.org\/10.1177\/10778010222183107","url":"http:\/\/journals.sagepub.com\/doi\/pdf\/10.1177\/10778010222183107"},"timestamp":"2018-08-09T12:53:16Z","relation_type_id":"references"},{"license":"https:\/\/creativecommons.org\/publicdomain\/zero\/1.0\/","obj_id":"https:\/\/doi.org\/10.1177\/10778010222183107","source_token":"36c35e23-8757-4a9d-aacf-345e9b7eb50d","occurred_at":"2018-08-13T18:40:47Z","subj_id":"https:\/\/en.wikipedia.org\/api\/rest_v1\/page\/html\/Anita_Raj_(academic)\/854780638","id":"a8678773-e730-49a6-a418-5c4f4025f0c4","evidence_record":"https:\/\/evidence.eventdata.crossref.org\/evidence\/20180813-wikipedia-db1c66b6-c305-4ca2-a504-48c390a39f75","terms":"https:\/\/doi.org\/10.13003\/CED-terms-of-use","action":"add","subj":{"pid":"https:\/\/en.wikipedia.org\/wiki\/Anita_Raj_(academic)","url":"https:\/\/en.wikipedia.org\/w\/index.php?title=Anita_Raj_(academic)&oldid=854780638","title":"Anita Raj (academic)","work_type_id":"entry-encyclopedia","api-url":"https:\/\/en.wikipedia.org\/api\/rest_v1\/page\/html\/Anita_Raj_(academic)\/854780638"},"source_id":"wikipedia","obj":{"pid":"https:\/\/doi.org\/10.1177\/10778010222183107","url":"http:\/\/journals.sagepub.com\/doi\/pdf\/10.1177\/10778010222183107"},"timestamp":"2018-08-13T18:41:41Z","relation_type_id":"references"},{"license":"https:\/\/creativecommons.org\/publicdomain\/zero\/1.0\/","obj_id":"https:\/\/doi.org\/10.1177\/10778010222183107","source_token":"36c35e23-8757-4a9d-aacf-345e9b7eb50d","occurred_at":"2018-08-13T19:03:46Z","subj_id":"https:\/\/en.wikipedia.org\/api\/rest_v1\/page\/html\/Anita_Raj_(academic)\/854783639","id":"46e93e1d-6f44-4541-b9eb-5e2e2dee7301","evidence_record":"https:\/\/evidence.eventdata.crossref.org\/evidence\/20180813-wikipedia-affb87a3-6177-43b0-9c39-82873e5c3702","terms":"https:\/\/doi.org\/10.13003\/CED-terms-of-use","action":"add","subj":{"pid":"https:\/\/en.wikipedia.org\/wiki\/Anita_Raj_(academic)","url":"https:\/\/en.wikipedia.org\/w\/index.php?title=Anita_Raj_(academic)&oldid=854783639","title":"Anita Raj (academic)","work_type_id":"entry-encyclopedia","api-url":"https:\/\/en.wikipedia.org\/api\/rest_v1\/page\/html\/Anita_Raj_(academic)\/854783639"},"source_id":"wikipedia","obj":{"pid":"https:\/\/doi.org\/10.1177\/10778010222183107","url":"http:\/\/journals.sagepub.com\/doi\/pdf\/10.1177\/10778010222183107"},"timestamp":"2018-08-13T19:05:27Z","relation_type_id":"references"},{"license":"https:\/\/creativecommons.org\/publicdomain\/zero\/1.0\/","obj_id":"https:\/\/doi.org\/10.1177\/10778010222183107","source_token":"36c35e23-8757-4a9d-aacf-345e9b7eb50d","occurred_at":"2018-08-13T20:46:33Z","subj_id":"https:\/\/en.wikipedia.org\/api\/rest_v1\/page\/html\/Anita_Raj_(academic)\/854795321","id":"658bbf34-dbae-4130-8d24-21840f4f851e","evidence_record":"https:\/\/evidence.eventdata.crossref.org\/evidence\/20180813-wikipedia-7030d323-e9d7-4843-964d-65fbee0991c0","terms":"https:\/\/doi.org\/10.13003\/CED-terms-of-use","action":"add","subj":{"pid":"https:\/\/en.wikipedia.org\/wiki\/Anita_Raj_(academic)","url":"https:\/\/en.wikipedia.org\/w\/index.php?title=Anita_Raj_(academic)&oldid=854795321","title":"Anita Raj (academic)","work_type_id":"entry-encyclopedia","api-url":"https:\/\/en.wikipedia.org\/api\/rest_v1\/page\/html\/Anita_Raj_(academic)\/854795321"},"source_id":"wikipedia","obj":{"pid":"https:\/\/doi.org\/10.1177\/10778010222183107","url":"http:\/\/journals.sagepub.com\/doi\/pdf\/10.1177\/10778010222183107"},"timestamp":"2018-08-13T20:48:52Z","relation_type_id":"references"},{"license":"https:\/\/creativecommons.org\/publicdomain\/zero\/1.0\/","obj_id":"https:\/\/doi.org\/10.1177\/10778010222183107","source_token":"36c35e23-8757-4a9d-aacf-345e9b7eb50d","occurred_at":"2018-08-17T18:41:12Z","subj_id":"https:\/\/en.wikipedia.org\/api\/rest_v1\/page\/html\/Anita_Raj_(academic)\/855360354","id":"92297487-e4c5-4deb-9424-27c5fcc6930b","evidence_record":"https:\/\/evidence.eventdata.crossref.org\/evidence\/20180817-wikipedia-fe292cf9-b7c2-42e4-a3a9-5d14ace01699","terms":"https:\/\/doi.org\/10.13003\/CED-terms-of-use","action":"add","subj":{"pid":"https:\/\/en.wikipedia.org\/wiki\/Anita_Raj_(academic)","url":"https:\/\/en.wikipedia.org\/w\/index.php?title=Anita_Raj_(academic)&oldid=855360354","title":"Anita Raj (academic)","work_type_id":"entry-encyclopedia","api-url":"https:\/\/en.wikipedia.org\/api\/rest_v1\/page\/html\/Anita_Raj_(academic)\/855360354"},"source_id":"wikipedia","obj":{"pid":"https:\/\/doi.org\/10.1177\/10778010222183107","url":"http:\/\/journals.sagepub.com\/doi\/pdf\/10.1177\/10778010222183107"},"timestamp":"2018-08-17T18:43:54Z","relation_type_id":"references"},{"license":"https:\/\/creativecommons.org\/publicdomain\/zero\/1.0\/","obj_id":"https:\/\/doi.org\/10.1177\/10778010222183107","source_token":"36c35e23-8757-4a9d-aacf-345e9b7eb50d","occurred_at":"2018-08-17T18:45:34Z","subj_id":"https:\/\/en.wikipedia.org\/api\/rest_v1\/page\/html\/Anita_Raj_(academic)\/855360943","id":"eb741eb0-633c-4787-b52c-358a2029452a","evidence_record":"https:\/\/evidence.eventdata.crossref.org\/evidence\/20180817-wikipedia-7bd1baa8-5917-49fb-bc5d-5e11a79316ff","terms":"https:\/\/doi.org\/10.13003\/CED-terms-of-use","action":"add","subj":{"pid":"https:\/\/en.wikipedia.org\/wiki\/Anita_Raj_(academic)","url":"https:\/\/en.wikipedia.org\/w\/index.php?title=Anita_Raj_(academic)&oldid=855360943","title":"Anita Raj (academic)","work_type_id":"entry-encyclopedia","api-url":"https:\/\/en.wikipedia.org\/api\/rest_v1\/page\/html\/Anita_Raj_(academic)\/855360943"},"source_id":"wikipedia","obj":{"pid":"https:\/\/doi.org\/10.1177\/10778010222183107","url":"http:\/\/journals.sagepub.com\/doi\/pdf\/10.1177\/10778010222183107"},"timestamp":"2018-08-17T18:47:27Z","relation_type_id":"references"},{"license":"https:\/\/creativecommons.org\/publicdomain\/zero\/1.0\/","obj_id":"https:\/\/doi.org\/10.1177\/10778010222183107","source_token":"36c35e23-8757-4a9d-aacf-345e9b7eb50d","occurred_at":"2018-08-17T18:42:42Z","subj_id":"https:\/\/en.wikipedia.org\/api\/rest_v1\/page\/html\/Anita_Raj_(academic)\/855360540","id":"871509f0-9292-4b1e-a818-1366fd69c5ae","evidence_record":"https:\/\/evidence.eventdata.crossref.org\/evidence\/20180817-wikipedia-89d8252b-fcd2-420e-9b08-055867f7399e","terms":"https:\/\/doi.org\/10.13003\/CED-terms-of-use","action":"add","subj":{"pid":"https:\/\/en.wikipedia.org\/wiki\/Anita_Raj_(academic)","url":"https:\/\/en.wikipedia.org\/w\/index.php?title=Anita_Raj_(academic)&oldid=855360540","title":"Anita Raj (academic)","work_type_id":"entry-encyclopedia","api-url":"https:\/\/en.wikipedia.org\/api\/rest_v1\/page\/html\/Anita_Raj_(academic)\/855360540"},"source_id":"wikipedia","obj":{"pid":"https:\/\/doi.org\/10.1177\/10778010222183107","url":"http:\/\/journals.sagepub.com\/doi\/pdf\/10.1177\/10778010222183107"},"timestamp":"2018-08-17T18:48:26Z","relation_type_id":"references"},{"license":"https:\/\/creativecommons.org\/publicdomain\/zero\/1.0\/","obj_id":"https:\/\/doi.org\/10.1177\/10778010222183107","source_token":"36c35e23-8757-4a9d-aacf-345e9b7eb50d","occurred_at":"2018-09-07T02:00:41Z","subj_id":"https:\/\/en.wikipedia.org\/api\/rest_v1\/page\/html\/Anita_Raj_(academic)\/858421358","id":"b0dadf11-978c-456b-a643-4cfa6a07b46e","evidence_record":"https:\/\/evidence.eventdata.crossref.org\/evidence\/20180907-wikipedia-6bd62415-7c7f-4cc0-95a8-b80b01121e71","terms":"https:\/\/doi.org\/10.13003\/CED-terms-of-use","action":"add","subj":{"pid":"https:\/\/en.wikipedia.org\/wiki\/Anita_Raj_(academic)","url":"https:\/\/en.wikipedia.org\/w\/index.php?title=Anita_Raj_(academic)&oldid=858421358","title":"Anita Raj (academic)","work_type_id":"entry-encyclopedia","api-url":"https:\/\/en.wikipedia.org\/api\/rest_v1\/page\/html\/Anita_Raj_(academic)\/858421358"},"source_id":"wikipedia","obj":{"pid":"https:\/\/doi.org\/10.1177\/10778010222183107","url":"http:\/\/journals.sagepub.com\/doi\/pdf\/10.1177\/10778010222183107"},"timestamp":"2018-09-07T02:02:05Z","relation_type_id":"references"},{"license":"https:\/\/creativecommons.org\/publicdomain\/zero\/1.0\/","obj_id":"https:\/\/doi.org\/10.1177\/10778010222183107","source_token":"36c35e23-8757-4a9d-aacf-345e9b7eb50d","occurred_at":"2018-09-29T03:02:12Z","subj_id":"https:\/\/en.wikipedia.org\/api\/rest_v1\/page\/html\/Anita_Raj_(academic)\/861665515","id":"bd139571-c761-459b-a498-015748282ac8","evidence_record":"https:\/\/evidence.eventdata.crossref.org\/evidence\/20180929-wikipedia-276e9de8-e7ae-4aa4-becc-983276d8a809","terms":"https:\/\/doi.org\/10.13003\/CED-terms-of-use","action":"add","subj":{"pid":"https:\/\/en.wikipedia.org\/wiki\/Anita_Raj_(academic)","url":"https:\/\/en.wikipedia.org\/w\/index.php?title=Anita_Raj_(academic)&oldid=861665515","title":"Anita Raj (academic)","work_type_id":"entry-encyclopedia","api-url":"https:\/\/en.wikipedia.org\/api\/rest_v1\/page\/html\/Anita_Raj_(academic)\/861665515"},"source_id":"wikipedia","obj":{"pid":"https:\/\/doi.org\/10.1177\/10778010222183107","url":"http:\/\/journals.sagepub.com\/doi\/pdf\/10.1177\/10778010222183107","method":"url-text","verification":"recognised-domain-prefix"},"timestamp":"2018-09-29T03:08:51Z","relation_type_id":"references"},{"license":"https:\/\/creativecommons.org\/publicdomain\/zero\/1.0\/","obj_id":"https:\/\/doi.org\/10.1177\/10778010222183107","source_token":"36c35e23-8757-4a9d-aacf-345e9b7eb50d","occurred_at":"2018-09-29T03:22:26Z","subj_id":"https:\/\/en.wikipedia.org\/api\/rest_v1\/page\/html\/Anita_Raj_(academic)\/861667248","id":"55498bff-1498-41e8-b720-ee0bf81b1636","evidence_record":"https:\/\/evidence.eventdata.crossref.org\/evidence\/20180929-wikipedia-1376567a-31dd-4264-9ab9-8c1177f15d69","terms":"https:\/\/doi.org\/10.13003\/CED-terms-of-use","action":"add","subj":{"pid":"https:\/\/en.wikipedia.org\/wiki\/Anita_Raj_(academic)","url":"https:\/\/en.wikipedia.org\/w\/index.php?title=Anita_Raj_(academic)&oldid=861667248","title":"Anita Raj (academic)","work_type_id":"entry-encyclopedia","api-url":"https:\/\/en.wikipedia.org\/api\/rest_v1\/page\/html\/Anita_Raj_(academic)\/861667248"},"source_id":"wikipedia","obj":{"pid":"https:\/\/doi.org\/10.1177\/10778010222183107","url":"http:\/\/journals.sagepub.com\/doi\/pdf\/10.1177\/10778010222183107","method":"url-text","verification":"recognised-domain-prefix"},"timestamp":"2018-09-29T03:25:07Z","relation_type_id":"references"},{"license":"https:\/\/creativecommons.org\/publicdomain\/zero\/1.0\/","obj_id":"https:\/\/doi.org\/10.1177\/10778010222183107","source_token":"36c35e23-8757-4a9d-aacf-345e9b7eb50d","occurred_at":"2019-01-28T02:22:45Z","subj_id":"https:\/\/en.wikipedia.org\/api\/rest_v1\/page\/html\/Anita_Raj_(academic)\/880560429","id":"a1334db2-5330-4067-a06b-cf607cc27e34","evidence_record":"https:\/\/evidence.eventdata.crossref.org\/evidence\/20190128-wikipedia-fd6d6b27-94af-422d-b8a5-e2a71dc01439","terms":"https:\/\/doi.org\/10.13003\/CED-terms-of-use","action":"add","subj":{"pid":"https:\/\/en.wikipedia.org\/wiki\/Anita_Raj_(academic)","url":"https:\/\/en.wikipedia.org\/w\/index.php?title=Anita_Raj_(academic)&oldid=880560429","title":"Anita Raj (academic)","work_type_id":"entry-encyclopedia","api-url":"https:\/\/en.wikipedia.org\/api\/rest_v1\/page\/html\/Anita_Raj_(academic)\/880560429"},"source_id":"wikipedia","obj":{"pid":"https:\/\/doi.org\/10.1177\/10778010222183107","url":"http:\/\/journals.sagepub.com\/doi\/pdf\/10.1177\/10778010222183107","method":"url-text","verification":"recognised-domain-prefix"},"timestamp":"2019-01-28T02:26:56Z","relation_type_id":"references"},{"license":"https:\/\/creativecommons.org\/publicdomain\/zero\/1.0\/","obj_id":"https:\/\/doi.org\/10.1177\/10778010222183107","source_token":"36c35e23-8757-4a9d-aacf-345e9b7eb50d","occurred_at":"2019-04-01T06:00:34Z","subj_id":"https:\/\/en.wikipedia.org\/api\/rest_v1\/page\/html\/Anita_Raj_(academic)\/890414203","id":"6a615dcc-d643-4f9d-b3d1-3e5f2d42c0ef","evidence_record":"https:\/\/evidence.eventdata.crossref.org\/evidence\/20190401-wikipedia-517623eb-2141-4455-af81-c6e24bfa71e2","terms":"https:\/\/doi.org\/10.13003\/CED-terms-of-use","action":"add","subj":{"pid":"https:\/\/en.wikipedia.org\/wiki\/Anita_Raj_(academic)","url":"https:\/\/en.wikipedia.org\/w\/index.php?title=Anita_Raj_(academic)&oldid=890414203","title":"Anita Raj (academic)","work_type_id":"entry-encyclopedia","api-url":"https:\/\/en.wikipedia.org\/api\/rest_v1\/page\/html\/Anita_Raj_(academic)\/890414203"},"source_id":"wikipedia","obj":{"pid":"https:\/\/doi.org\/10.1177\/10778010222183107","url":"http:\/\/journals.sagepub.com\/doi\/pdf\/10.1177\/10778010222183107","method":"url-text","verification":"recognised-domain-prefix"},"timestamp":"2019-04-01T06:03:18Z","relation_type_id":"references"},{"license":"https:\/\/creativecommons.org\/publicdomain\/zero\/1.0\/","obj_id":"https:\/\/doi.org\/10.1177\/10778010222183107","source_token":"45a1ef76-4f43-4cdc-9ba8-5a6ad01cc231","occurred_at":"2019-05-01T19:45:09Z","subj_id":"twitter:\/\/status?id=1123674739749289985","id":"5e190e97-7875-46d7-b254-898a26ac9e9a","evidence_record":"https:\/\/evidence.eventdata.crossref.org\/evidence\/20190501-twitter-91c5a5c9-74ae-4169-baf7-79c9a46f0f04","terms":"https:\/\/doi.org\/10.13003\/CED-terms-of-use","action":"add","subj":{"pid":"twitter:\/\/status?id=1123674739749289985","url":"twitter:\/\/status?id=1123674739749289985","title":"Tweet 1123674739749289985","issued":"2019-05-01T19:45:09.000Z","author":{"url":"twitter:\/\/user?screen_name=OmellDaniel"},"original-tweet-url":"twitter:\/\/status?id=1123674739749289985","original-tweet-author":null,"alternative-id":"1123674739749289985"},"source_id":"twitter","obj":{"pid":"https:\/\/doi.org\/10.1177\/10778010222183107","url":"https:\/\/journals.sagepub.com\/doi\/abs\/10.1177\/10778010222183107#articleShareContainer","method":"url-text","verification":"recognised-domain-prefix"},"timestamp":"2019-05-01T22:47:04Z","relation_type_id":"discusses"},{"license":"https:\/\/doi.org\/10.13003\/CED-terms-of-use","obj_id":"https:\/\/doi.org\/10.1177\/10778010222183107","source_token":"8676e950-8ac5-4074-8ac3-c0a18ada7e99","occurred_at":"2012-03-01T00:00:00Z","subj_id":"https:\/\/doi.org\/10.1080\/0735648X.2011.631393","id":"82d9cee2-782f-4e63-8c5c-fc004dfbef2e","terms":"https:\/\/doi.org\/10.13003\/CED-terms-of-use","message_action":"create","source_id":"crossref","timestamp":"2019-06-24T00:15:07Z","relation_type_id":"references"},{"license":"https:\/\/doi.org\/10.13003\/CED-terms-of-use","obj_id":"https:\/\/doi.org\/10.1177\/10778010222183107","source_token":"8676e950-8ac5-4074-8ac3-c0a18ada7e99","occurred_at":"2018-08-13T00:00:00Z","subj_id":"https:\/\/doi.org\/10.1007\/s10903-018-0803-9","id":"ba9fe5a9-8ede-46c3-8174-c25f1b889ad1","terms":"https:\/\/doi.org\/10.13003\/CED-terms-of-use","message_action":"create","source_id":"crossref","timestamp":"2019-06-29T20:17:31Z","relation_type_id":"references"},{"license":"https:\/\/doi.org\/10.13003\/CED-terms-of-use","obj_id":"https:\/\/doi.org\/10.1177\/10778010222183107","source_token":"8676e950-8ac5-4074-8ac3-c0a18ada7e99","occurred_at":"2012-07-15T00:00:00Z","subj_id":"https:\/\/doi.org\/10.1080\/01900692.2012.661191","id":"a20d3a63-8b40-4e5b-b498-7b05dda8eb92","terms":"https:\/\/doi.org\/10.13003\/CED-terms-of-use","message_action":"create","source_id":"crossref","timestamp":"2019-07-02T21:19:12Z","relation_type_id":"references"},{"license":"https:\/\/doi.org\/10.13003\/CED-terms-of-use","obj_id":"https:\/\/doi.org\/10.1177\/10778010222183107","source_token":"8676e950-8ac5-4074-8ac3-c0a18ada7e99","occurred_at":"2012-11-01T00:00:00Z","subj_id":"https:\/\/doi.org\/10.1177\/1477370812453410","id":"2645919a-f038-45ce-9dce-5863b65fe433","terms":"https:\/\/doi.org\/10.13003\/CED-terms-of-use","message_action":"create","source_id":"crossref","timestamp":"2019-07-07T04:54:50Z","relation_type_id":"references"},{"license":"https:\/\/doi.org\/10.13003\/CED-terms-of-use","obj_id":"https:\/\/doi.org\/10.1177\/10778010222183107","source_token":"8676e950-8ac5-4074-8ac3-c0a18ada7e99","occurred_at":"2012-11-25T00:00:00Z","subj_id":"https:\/\/doi.org\/10.1007\/s11199-012-0246-z","id":"a6a1c838-6360-44a5-8cdd-5ccd2fd7a5d1","terms":"https:\/\/doi.org\/10.13003\/CED-terms-of-use","message_action":"create","source_id":"crossref","timestamp":"2019-07-08T01:20:09Z","relation_type_id":"references"},{"license":"https:\/\/doi.org\/10.13003\/CED-terms-of-use","obj_id":"https:\/\/doi.org\/10.1177\/10778010222183107","source_token":"8676e950-8ac5-4074-8ac3-c0a18ada7e99","occurred_at":"2013-03-01T00:00:00Z","subj_id":"https:\/\/doi.org\/10.1080\/19438192.2013.722383","id":"ddfb65ce-c4da-4f81-bdca-19819e66b339","terms":"https:\/\/doi.org\/10.13003\/CED-terms-of-use","message_action":"create","source_id":"crossref","timestamp":"2019-07-10T03:42:43Z","relation_type_id":"references"},{"license":"https:\/\/doi.org\/10.13003\/CED-terms-of-use","obj_id":"https:\/\/doi.org\/10.1177\/10778010222183107","source_token":"8676e950-8ac5-4074-8ac3-c0a18ada7e99","occurred_at":"2013-01-01T00:00:00Z","subj_id":"https:\/\/doi.org\/10.1891\/1946-6560.4.3.295","id":"16a54fb1-563e-469c-86cd-45cfef251fdd","terms":"https:\/\/doi.org\/10.13003\/CED-terms-of-use","message_action":"create","source_id":"crossref","timestamp":"2019-07-22T14:36:07Z","relation_type_id":"references"},{"license":"https:\/\/creativecommons.org\/publicdomain\/zero\/1.0\/","obj_id":"https:\/\/doi.org\/10.1177\/10778010222183107","source_token":"36c35e23-8757-4a9d-aacf-345e9b7eb50d","occurred_at":"2019-09-29T06:24:40Z","subj_id":"https:\/\/en.wikipedia.org\/api\/rest_v1\/page\/html\/Anita_Raj_(academic)\/918548900","id":"d6d6bcf0-e856-4e76-955a-6dfd72a7dead","evidence_record":"https:\/\/evidence.eventdata.crossref.org\/evidence\/20190929-wikipedia-45b02023-97fe-45d2-8268-50298a2dcf6c","terms":"https:\/\/doi.org\/10.13003\/CED-terms-of-use","action":"add","subj":{"pid":"https:\/\/en.wikipedia.org\/wiki\/Anita_Raj_(academic)","url":"https:\/\/en.wikipedia.org\/w\/index.php?title=Anita_Raj_(academic)&oldid=918548900","title":"Anita Raj (academic)","work_type_id":"entry-encyclopedia","api-url":"https:\/\/en.wikipedia.org\/api\/rest_v1\/page\/html\/Anita_Raj_(academic)\/918548900"},"source_id":"wikipedia","obj":{"pid":"https:\/\/doi.org\/10.1177\/10778010222183107","url":"http:\/\/journals.sagepub.com\/doi\/pdf\/10.1177\/10778010222183107","method":"url-text","verification":"recognised-domain-prefix"},"timestamp":"2019-09-29T06:29:41Z","relation_type_id":"references"},{"license":"https:\/\/doi.org\/10.13003\/CED-terms-of-use","obj_id":"https:\/\/doi.org\/10.1177\/10778010222183107","source_token":"8676e950-8ac5-4074-8ac3-c0a18ada7e99","occurred_at":"2012-09-29T00:00:00Z","subj_id":"https:\/\/doi.org\/10.1007\/s10903-012-9725-0","id":"da5efb88-90df-4e40-a761-2092225f067a","terms":"https:\/\/doi.org\/10.13003\/CED-terms-of-use","message_action":"create","source_id":"crossref","timestamp":"2019-10-15T21:02:57Z","relation_type_id":"references"},{"license":"https:\/\/doi.org\/10.13003\/CED-terms-of-use","obj_id":"https:\/\/doi.org\/10.1177\/10778010222183107","source_token":"8676e950-8ac5-4074-8ac3-c0a18ada7e99","occurred_at":"2012-07-31T00:00:00Z","subj_id":"https:\/\/doi.org\/10.1007\/s00737-012-0298-7","id":"09a9c642-5ca9-4cb0-b6d6-889ca1e09ed5","terms":"https:\/\/doi.org\/10.13003\/CED-terms-of-use","message_action":"create","source_id":"crossref","timestamp":"2019-10-16T18:28:07Z","relation_type_id":"references"},{"license":"https:\/\/doi.org\/10.13003\/CED-terms-of-use","obj_id":"https:\/\/doi.org\/10.1177\/10778010222183107","source_token":"8676e950-8ac5-4074-8ac3-c0a18ada7e99","occurred_at":"2019-01-20T00:00:00Z","subj_id":"https:\/\/doi.org\/10.1111\/soin.12265","id":"6b08d92b-5d98-495b-a204-47ee73f71d1f","terms":"https:\/\/doi.org\/10.13003\/CED-terms-of-use","message_action":"create","source_id":"crossref","timestamp":"2019-11-24T20:46:25Z","relation_type_id":"references"},{"license":"https:\/\/doi.org\/10.13003\/CED-terms-of-use","obj_id":"https:\/\/doi.org\/10.1177\/10778010222183107","source_token":"8676e950-8ac5-4074-8ac3-c0a18ada7e99","occurred_at":"2019-01-01T00:00:00Z","subj_id":"https:\/\/doi.org\/10.1590\/0102.3772e3549","id":"b9d704db-f1de-4349-880e-a6d183a9751a","terms":"https:\/\/doi.org\/10.13003\/CED-terms-of-use","message_action":"create","source_id":"crossref","timestamp":"2019-12-02T08:41:34Z","relation_type_id":"references"},{"license":"https:\/\/creativecommons.org\/publicdomain\/zero\/1.0\/","obj_id":"https:\/\/doi.org\/10.1177\/10778010222183107","source_token":"36c35e23-8757-4a9d-aacf-345e9b7eb50d","occurred_at":"2019-12-07T11:18:02Z","subj_id":"https:\/\/en.wikipedia.org\/api\/rest_v1\/page\/html\/Anita_Raj_(academic)\/929668347","id":"cfdbd9d8-a4b4-4371-99f4-af7365a834d4","evidence_record":"https:\/\/evidence.eventdata.crossref.org\/evidence\/20191207-wikipedia-5bbe7bf4-0c43-43ca-9e4e-2dc76772e3bd","terms":"https:\/\/doi.org\/10.13003\/CED-terms-of-use","action":"add","subj":{"pid":"https:\/\/en.wikipedia.org\/wiki\/Anita_Raj_(academic)","url":"https:\/\/en.wikipedia.org\/w\/index.php?title=Anita_Raj_(academic)&oldid=929668347","title":"Anita Raj (academic)","work_type_id":"entry-encyclopedia","api-url":"https:\/\/en.wikipedia.org\/api\/rest_v1\/page\/html\/Anita_Raj_(academic)\/929668347"},"source_id":"wikipedia","obj":{"pid":"https:\/\/doi.org\/10.1177\/10778010222183107","url":"http:\/\/journals.sagepub.com\/doi\/pdf\/10.1177\/10778010222183107","method":"url-text","verification":"recognised-domain-prefix"},"timestamp":"2019-12-07T11:37:01Z","relation_type_id":"references"},{"license":"https:\/\/creativecommons.org\/publicdomain\/zero\/1.0\/","obj_id":"https:\/\/doi.org\/10.1177\/10778010222183107","source_token":"36c35e23-8757-4a9d-aacf-345e9b7eb50d","occurred_at":"2019-12-07T11:18:02Z","subj_id":"https:\/\/en.wikipedia.org\/api\/rest_v1\/page\/html\/Anita_Raj_(academic)\/929668347","id":"2b5f8d97-23f2-4624-a4d6-d144fad225db","evidence_record":"https:\/\/evidence.eventdata.crossref.org\/evidence\/20191208-wikipedia-716a9093-efe1-4052-a338-ba2043a12ace","terms":"https:\/\/doi.org\/10.13003\/CED-terms-of-use","action":"add","subj":{"pid":"https:\/\/en.wikipedia.org\/wiki\/Anita_Raj_(academic)","url":"https:\/\/en.wikipedia.org\/w\/index.php?title=Anita_Raj_(academic)&oldid=929668347","title":"Anita Raj (academic)","work_type_id":"entry-encyclopedia","api-url":"https:\/\/en.wikipedia.org\/api\/rest_v1\/page\/html\/Anita_Raj_(academic)\/929668347"},"source_id":"wikipedia","obj":{"pid":"https:\/\/doi.org\/10.1177\/10778010222183107","url":"http:\/\/journals.sagepub.com\/doi\/pdf\/10.1177\/10778010222183107","method":"url-text","verification":"recognised-domain-prefix"},"timestamp":"2019-12-13T19:37:26Z","relation_type_id":"references"},{"license":"https:\/\/doi.org\/10.13003\/CED-terms-of-use","obj_id":"https:\/\/doi.org\/10.1177\/10778010222183107","source_token":"8676e950-8ac5-4074-8ac3-c0a18ada7e99","occurred_at":"2017-01-30T00:00:00Z","subj_id":"https:\/\/doi.org\/10.1177\/0886260517689886","id":"b4f30452-bded-491c-915d-00b44c6b6c60","terms":"https:\/\/doi.org\/10.13003\/CED-terms-of-use","message_action":"create","source_id":"crossref","timestamp":"2020-01-11T03:00:09Z","relation_type_id":"references"},{"license":"https:\/\/creativecommons.org\/publicdomain\/zero\/1.0\/","obj_id":"https:\/\/doi.org\/10.1177\/10778010222183107","source_token":"36c35e23-8757-4a9d-aacf-345e9b7eb50d","occurred_at":"2020-02-07T19:50:34Z","subj_id":"https:\/\/en.wikipedia.org\/api\/rest_v1\/page\/html\/Anita_Raj_(academic)\/939646748","id":"244cadd6-dd7d-4b26-ac3a-d73f59d3758c","evidence_record":"https:\/\/evidence.eventdata.crossref.org\/evidence\/20200207-wikipedia-18e462e0-d9d7-44af-83dd-7187dc43b23c","terms":"https:\/\/doi.org\/10.13003\/CED-terms-of-use","action":"add","subj":{"pid":"https:\/\/en.wikipedia.org\/wiki\/Anita_Raj_(academic)","url":"https:\/\/en.wikipedia.org\/w\/index.php?title=Anita_Raj_(academic)&oldid=939646748","title":"Anita Raj (academic)","work_type_id":"entry-encyclopedia","api-url":"https:\/\/en.wikipedia.org\/api\/rest_v1\/page\/html\/Anita_Raj_(academic)\/939646748"},"source_id":"wikipedia","obj":{"pid":"https:\/\/doi.org\/10.1177\/10778010222183107","url":"http:\/\/journals.sagepub.com\/doi\/pdf\/10.1177\/10778010222183107","method":"url-text","verification":"recognised-domain-prefix"},"timestamp":"2020-02-07T19:54:45Z","relation_type_id":"references"},{"license":"https:\/\/creativecommons.org\/publicdomain\/zero\/1.0\/","obj_id":"https:\/\/doi.org\/10.1177\/10778010222183107","source_token":"36c35e23-8757-4a9d-aacf-345e9b7eb50d","occurred_at":"2020-06-01T05:05:49Z","subj_id":"https:\/\/en.wikipedia.org\/api\/rest_v1\/page\/html\/Anita_Raj_(academic)\/960110037","id":"5753b404-f60d-4e31-a65d-51ef9da5b7a7","evidence_record":"https:\/\/evidence.eventdata.crossref.org\/evidence\/20200601-wikipedia-8e0a1a01-27f3-4d55-9cf4-a1decf52f6d2","terms":"https:\/\/doi.org\/10.13003\/CED-terms-of-use","action":"add","subj":{"pid":"https:\/\/en.wikipedia.org\/wiki\/Anita_Raj_(academic)","url":"https:\/\/en.wikipedia.org\/w\/index.php?title=Anita_Raj_(academic)&oldid=960110037","title":"Anita Raj (academic)","work_type_id":"entry-encyclopedia","api-url":"https:\/\/en.wikipedia.org\/api\/rest_v1\/page\/html\/Anita_Raj_(academic)\/960110037"},"source_id":"wikipedia","obj":{"pid":"https:\/\/doi.org\/10.1177\/10778010222183107","url":"https:\/\/doi.org\/10.1177\/10778010222183107","method":"doi-literal","verification":"literal"},"timestamp":"2020-10-12T16:16:09Z","relation_type_id":"references"},{"license":"https:\/\/creativecommons.org\/publicdomain\/zero\/1.0\/","obj_id":"https:\/\/doi.org\/10.1177\/10778010222183107","source_token":"36c35e23-8757-4a9d-aacf-345e9b7eb50d","occurred_at":"2020-04-12T11:18:25Z","subj_id":"https:\/\/en.wikipedia.org\/api\/rest_v1\/page\/html\/Anita_Raj_(academic)\/950499923","id":"789dfd67-bf3b-495b-8414-9121a035cdd5","evidence_record":"https:\/\/evidence.eventdata.crossref.org\/evidence\/20200412-wikipedia-5ab36e30-7aa6-4ff8-be79-f5e821395aff","terms":"https:\/\/doi.org\/10.13003\/CED-terms-of-use","action":"add","subj":{"pid":"https:\/\/en.wikipedia.org\/wiki\/Anita_Raj_(academic)","url":"https:\/\/en.wikipedia.org\/w\/index.php?title=Anita_Raj_(academic)&oldid=950499923","title":"Anita Raj (academic)","work_type_id":"entry-encyclopedia","api-url":"https:\/\/en.wikipedia.org\/api\/rest_v1\/page\/html\/Anita_Raj_(academic)\/950499923"},"source_id":"wikipedia","obj":{"pid":"https:\/\/doi.org\/10.1177\/10778010222183107","url":"http:\/\/journals.sagepub.com\/doi\/pdf\/10.1177\/10778010222183107","method":"url-text","verification":"recognised-domain-prefix"},"timestamp":"2020-10-14T07:19:24Z","relation_type_id":"references"},{"license":"https:\/\/creativecommons.org\/publicdomain\/zero\/1.0\/","obj_id":"https:\/\/doi.org\/10.1177\/10778010222183107","source_token":"36c35e23-8757-4a9d-aacf-345e9b7eb50d","occurred_at":"2020-04-12T11:19:33Z","subj_id":"https:\/\/en.wikipedia.org\/api\/rest_v1\/page\/html\/Anita_Raj_(academic)\/950500052","id":"eb2839d2-e2ee-4754-b0cd-8550d969a4ae","evidence_record":"https:\/\/evidence.eventdata.crossref.org\/evidence\/20200412-wikipedia-961cf0b9-25ca-4308-a784-3cecb9363337","terms":"https:\/\/doi.org\/10.13003\/CED-terms-of-use","action":"add","subj":{"pid":"https:\/\/en.wikipedia.org\/wiki\/Anita_Raj_(academic)","url":"https:\/\/en.wikipedia.org\/w\/index.php?title=Anita_Raj_(academic)&oldid=950500052","title":"Anita Raj (academic)","work_type_id":"entry-encyclopedia","api-url":"https:\/\/en.wikipedia.org\/api\/rest_v1\/page\/html\/Anita_Raj_(academic)\/950500052"},"source_id":"wikipedia","obj":{"pid":"https:\/\/doi.org\/10.1177\/10778010222183107","url":"http:\/\/journals.sagepub.com\/doi\/pdf\/10.1177\/10778010222183107","method":"url-text","verification":"recognised-domain-prefix"},"timestamp":"2020-10-14T07:26:12Z","relation_type_id":"references"},{"license":"https:\/\/creativecommons.org\/publicdomain\/zero\/1.0\/","obj_id":"https:\/\/doi.org\/10.1177\/10778010222183107","source_token":"36c35e23-8757-4a9d-aacf-345e9b7eb50d","occurred_at":"2020-04-12T11:19:33Z","subj_id":"https:\/\/en.wikipedia.org\/api\/rest_v1\/page\/html\/Anita_Raj_(academic)\/950500052","id":"b0f9fcbe-c628-46f4-b741-5155f6fa985a","evidence_record":"https:\/\/evidence.eventdata.crossref.org\/evidence\/20200412-wikipedia-961cf0b9-25ca-4308-a784-3cecb9363337","terms":"https:\/\/doi.org\/10.13003\/CED-terms-of-use","action":"add","subj":{"pid":"https:\/\/en.wikipedia.org\/wiki\/Anita_Raj_(academic)","url":"https:\/\/en.wikipedia.org\/w\/index.php?title=Anita_Raj_(academic)&oldid=950500052","title":"Anita Raj (academic)","work_type_id":"entry-encyclopedia","api-url":"https:\/\/en.wikipedia.org\/api\/rest_v1\/page\/html\/Anita_Raj_(academic)\/950500052"},"source_id":"wikipedia","obj":{"pid":"https:\/\/doi.org\/10.1177\/10778010222183107","url":"https:\/\/doi.org\/10.1177\/10778010222183107","method":"doi-literal","verification":"literal"},"timestamp":"2020-10-14T07:26:12Z","relation_type_id":"references"},{"license":"https:\/\/creativecommons.org\/publicdomain\/zero\/1.0\/","obj_id":"https:\/\/doi.org\/10.1177\/10778010222183107","source_token":"36c35e23-8757-4a9d-aacf-345e9b7eb50d","occurred_at":"2020-04-29T01:08:05Z","subj_id":"https:\/\/en.wikipedia.org\/api\/rest_v1\/page\/html\/Anita_Raj_(academic)\/953780895","id":"7f3c86dc-1947-449d-91ca-f1e900dab420","evidence_record":"https:\/\/evidence.eventdata.crossref.org\/evidence\/20200429-wikipedia-26dc9ebc-d97e-4ae7-a576-e861f73375f1","terms":"https:\/\/doi.org\/10.13003\/CED-terms-of-use","action":"add","subj":{"pid":"https:\/\/en.wikipedia.org\/wiki\/Anita_Raj_(academic)","url":"https:\/\/en.wikipedia.org\/w\/index.php?title=Anita_Raj_(academic)&oldid=953780895","title":"Anita Raj (academic)","work_type_id":"entry-encyclopedia","api-url":"https:\/\/en.wikipedia.org\/api\/rest_v1\/page\/html\/Anita_Raj_(academic)\/953780895"},"source_id":"wikipedia","obj":{"pid":"https:\/\/doi.org\/10.1177\/10778010222183107","url":"https:\/\/doi.org\/10.1177\/10778010222183107","method":"doi-literal","verification":"literal"},"timestamp":"2020-10-14T16:01:17Z","relation_type_id":"references"},{"license":"https:\/\/creativecommons.org\/publicdomain\/zero\/1.0\/","obj_id":"https:\/\/doi.org\/10.1177\/10778010222183107","source_token":"36c35e23-8757-4a9d-aacf-345e9b7eb50d","occurred_at":"2020-06-25T08:05:47Z","subj_id":"https:\/\/en.wikipedia.org\/api\/rest_v1\/page\/html\/Anita_Raj_(academic)\/964397680","id":"4e3e27b2-119d-409f-b8ec-6bef4e37a2fe","evidence_record":"https:\/\/evidence.eventdata.crossref.org\/evidence\/20200625-wikipedia-b94d5420-287f-4518-b460-19613d1aae88","terms":"https:\/\/doi.org\/10.13003\/CED-terms-of-use","action":"add","subj":{"pid":"https:\/\/en.wikipedia.org\/wiki\/Anita_Raj_(academic)","url":"https:\/\/en.wikipedia.org\/w\/index.php?title=Anita_Raj_(academic)&oldid=964397680","title":"Anita Raj (academic)","work_type_id":"entry-encyclopedia","api-url":"https:\/\/en.wikipedia.org\/api\/rest_v1\/page\/html\/Anita_Raj_(academic)\/964397680"},"source_id":"wikipedia","obj":{"pid":"https:\/\/doi.org\/10.1177\/10778010222183107","url":"https:\/\/doi.org\/10.1177\/10778010222183107","method":"doi-literal","verification":"literal"},"timestamp":"2020-10-15T19:42:35Z","relation_type_id":"references"},{"license":"https:\/\/creativecommons.org\/publicdomain\/zero\/1.0\/","obj_id":"https:\/\/doi.org\/10.1177\/10778010222183107","source_token":"36c35e23-8757-4a9d-aacf-345e9b7eb50d","occurred_at":"2020-07-14T00:07:35Z","subj_id":"https:\/\/en.wikipedia.org\/api\/rest_v1\/page\/html\/Anita_Raj_(academic)\/967560516","id":"5e76b48f-76ad-48e3-a8a6-17193eeb41bc","evidence_record":"https:\/\/evidence.eventdata.crossref.org\/evidence\/20200714-wikipedia-904eaaa8-27d0-4823-9f27-e7106d3f9e5c","terms":"https:\/\/doi.org\/10.13003\/CED-terms-of-use","action":"add","subj":{"pid":"https:\/\/en.wikipedia.org\/wiki\/Anita_Raj_(academic)","url":"https:\/\/en.wikipedia.org\/w\/index.php?title=Anita_Raj_(academic)&oldid=967560516","title":"Anita Raj (academic)","work_type_id":"entry-encyclopedia","api-url":"https:\/\/en.wikipedia.org\/api\/rest_v1\/page\/html\/Anita_Raj_(academic)\/967560516"},"source_id":"wikipedia","obj":{"pid":"https:\/\/doi.org\/10.1177\/10778010222183107","url":"https:\/\/doi.org\/10.1177\/10778010222183107","method":"doi-literal","verification":"literal"},"timestamp":"2020-10-16T05:46:54Z","relation_type_id":"references"},{"license":"https:\/\/creativecommons.org\/publicdomain\/zero\/1.0\/","obj_id":"https:\/\/doi.org\/10.1177\/10778010222183107","source_token":"36c35e23-8757-4a9d-aacf-345e9b7eb50d","occurred_at":"2020-07-14T00:09:30Z","subj_id":"https:\/\/en.wikipedia.org\/api\/rest_v1\/page\/html\/Anita_Raj_(academic)\/967560688","id":"d10f7809-0225-4f4e-b657-f1156238087c","evidence_record":"https:\/\/evidence.eventdata.crossref.org\/evidence\/20200714-wikipedia-bc838a2f-3395-461c-a222-fad3802794d4","terms":"https:\/\/doi.org\/10.13003\/CED-terms-of-use","action":"add","subj":{"pid":"https:\/\/en.wikipedia.org\/wiki\/Anita_Raj_(academic)","url":"https:\/\/en.wikipedia.org\/w\/index.php?title=Anita_Raj_(academic)&oldid=967560688","title":"Anita Raj (academic)","work_type_id":"entry-encyclopedia","api-url":"https:\/\/en.wikipedia.org\/api\/rest_v1\/page\/html\/Anita_Raj_(academic)\/967560688"},"source_id":"wikipedia","obj":{"pid":"https:\/\/doi.org\/10.1177\/10778010222183107","url":"https:\/\/doi.org\/10.1177\/10778010222183107","method":"doi-literal","verification":"literal"},"timestamp":"2020-10-16T05:51:05Z","relation_type_id":"references"},{"license":"https:\/\/creativecommons.org\/publicdomain\/zero\/1.0\/","obj_id":"https:\/\/doi.org\/10.1177\/10778010222183107","source_token":"36c35e23-8757-4a9d-aacf-345e9b7eb50d","occurred_at":"2020-07-14T00:07:35Z","subj_id":"https:\/\/en.wikipedia.org\/api\/rest_v1\/page\/html\/Anita_Raj_(academic)\/967560516","id":"4bd52f5b-72ca-43c2-823e-c2498ab417e4","evidence_record":"https:\/\/evidence.eventdata.crossref.org\/evidence\/20200718-wikipedia-6cd47458-927b-428d-852e-bc732f4baf8d","terms":"https:\/\/doi.org\/10.13003\/CED-terms-of-use","action":"add","subj":{"pid":"https:\/\/en.wikipedia.org\/wiki\/Anita_Raj_(academic)","url":"https:\/\/en.wikipedia.org\/w\/index.php?title=Anita_Raj_(academic)&oldid=967560516","title":"Anita Raj (academic)","work_type_id":"entry-encyclopedia","api-url":"https:\/\/en.wikipedia.org\/api\/rest_v1\/page\/html\/Anita_Raj_(academic)\/967560516"},"source_id":"wikipedia","obj":{"pid":"https:\/\/doi.org\/10.1177\/10778010222183107","url":"https:\/\/doi.org\/10.1177\/10778010222183107","method":"doi-literal","verification":"literal"},"timestamp":"2020-10-16T09:12:33Z","relation_type_id":"references"},{"license":"https:\/\/creativecommons.org\/publicdomain\/zero\/1.0\/","obj_id":"https:\/\/doi.org\/10.1177\/10778010222183107","source_token":"36c35e23-8757-4a9d-aacf-345e9b7eb50d","occurred_at":"2020-07-14T00:09:30Z","subj_id":"https:\/\/en.wikipedia.org\/api\/rest_v1\/page\/html\/Anita_Raj_(academic)\/967560688","id":"4530b866-12aa-4d09-8d0f-6b55a7e81073","evidence_record":"https:\/\/evidence.eventdata.crossref.org\/evidence\/20200718-wikipedia-93f881af-3a1d-4b4b-aaaf-f0c0778d37bc","terms":"https:\/\/doi.org\/10.13003\/CED-terms-of-use","action":"add","subj":{"pid":"https:\/\/en.wikipedia.org\/wiki\/Anita_Raj_(academic)","url":"https:\/\/en.wikipedia.org\/w\/index.php?title=Anita_Raj_(academic)&oldid=967560688","title":"Anita Raj (academic)","work_type_id":"entry-encyclopedia","api-url":"https:\/\/en.wikipedia.org\/api\/rest_v1\/page\/html\/Anita_Raj_(academic)\/967560688"},"source_id":"wikipedia","obj":{"pid":"https:\/\/doi.org\/10.1177\/10778010222183107","url":"https:\/\/doi.org\/10.1177\/10778010222183107","method":"doi-literal","verification":"literal"},"timestamp":"2020-10-16T09:57:55Z","relation_type_id":"references"},{"license":"https:\/\/creativecommons.org\/publicdomain\/zero\/1.0\/","obj_id":"https:\/\/doi.org\/10.1177\/10778010222183107","source_token":"36c35e23-8757-4a9d-aacf-345e9b7eb50d","occurred_at":"2020-07-17T22:04:11Z","subj_id":"https:\/\/en.wikipedia.org\/api\/rest_v1\/page\/html\/Anita_Raj_(academic)\/968205074","id":"715af1d8-a5de-4e40-bf16-1e673b26fb4c","evidence_record":"https:\/\/evidence.eventdata.crossref.org\/evidence\/20200808-wikipedia-23536e15-28b9-4012-9f76-38aa3b76be7d","terms":"https:\/\/doi.org\/10.13003\/CED-terms-of-use","action":"add","subj":{"pid":"https:\/\/en.wikipedia.org\/wiki\/Anita_Raj_(academic)","url":"https:\/\/en.wikipedia.org\/w\/index.php?title=Anita_Raj_(academic)&oldid=968205074","title":"Anita Raj (academic)","work_type_id":"entry-encyclopedia","api-url":"https:\/\/en.wikipedia.org\/api\/rest_v1\/page\/html\/Anita_Raj_(academic)\/968205074"},"source_id":"wikipedia","obj":{"pid":"https:\/\/doi.org\/10.1177\/10778010222183107","url":"https:\/\/doi.org\/10.1177\/10778010222183107","method":"doi-literal","verification":"literal"},"timestamp":"2020-10-16T20:34:38Z","relation_type_id":"references"},{"license":"https:\/\/creativecommons.org\/publicdomain\/zero\/1.0\/","obj_id":"https:\/\/doi.org\/10.1177\/10778010222183107","source_token":"36c35e23-8757-4a9d-aacf-345e9b7eb50d","occurred_at":"2020-07-14T00:07:35Z","subj_id":"https:\/\/en.wikipedia.org\/api\/rest_v1\/page\/html\/Anita_Raj_(academic)\/967560516","id":"faba8a68-3fd4-4e90-b617-a1c76d95373c","evidence_record":"https:\/\/evidence.eventdata.crossref.org\/evidence\/20200808-wikipedia-7e2a89d1-8aaf-498e-97e5-561266b2879e","terms":"https:\/\/doi.org\/10.13003\/CED-terms-of-use","action":"add","subj":{"pid":"https:\/\/en.wikipedia.org\/wiki\/Anita_Raj_(academic)","url":"https:\/\/en.wikipedia.org\/w\/index.php?title=Anita_Raj_(academic)&oldid=967560516","title":"Anita Raj (academic)","work_type_id":"entry-encyclopedia","api-url":"https:\/\/en.wikipedia.org\/api\/rest_v1\/page\/html\/Anita_Raj_(academic)\/967560516"},"source_id":"wikipedia","obj":{"pid":"https:\/\/doi.org\/10.1177\/10778010222183107","url":"https:\/\/doi.org\/10.1177\/10778010222183107","method":"doi-literal","verification":"literal"},"timestamp":"2020-10-16T22:22:38Z","relation_type_id":"references"},{"license":"https:\/\/creativecommons.org\/publicdomain\/zero\/1.0\/","obj_id":"https:\/\/doi.org\/10.1177\/10778010222183107","source_token":"36c35e23-8757-4a9d-aacf-345e9b7eb50d","occurred_at":"2020-07-17T22:04:28Z","subj_id":"https:\/\/en.wikipedia.org\/api\/rest_v1\/page\/html\/Anita_Raj_(academic)\/968205101","id":"5a8ef186-ce1c-420c-acd1-93c4d69dcd7e","evidence_record":"https:\/\/evidence.eventdata.crossref.org\/evidence\/20200808-wikipedia-8b037daf-2d12-4d35-9c77-8f28516efe99","terms":"https:\/\/doi.org\/10.13003\/CED-terms-of-use","action":"add","subj":{"pid":"https:\/\/en.wikipedia.org\/wiki\/Anita_Raj_(academic)","url":"https:\/\/en.wikipedia.org\/w\/index.php?title=Anita_Raj_(academic)&oldid=968205101","title":"Anita Raj (academic)","work_type_id":"entry-encyclopedia","api-url":"https:\/\/en.wikipedia.org\/api\/rest_v1\/page\/html\/Anita_Raj_(academic)\/968205101"},"source_id":"wikipedia","obj":{"pid":"https:\/\/doi.org\/10.1177\/10778010222183107","url":"https:\/\/doi.org\/10.1177\/10778010222183107","method":"doi-literal","verification":"literal"},"timestamp":"2020-10-16T22:38:44Z","relation_type_id":"references"},{"license":"https:\/\/creativecommons.org\/publicdomain\/zero\/1.0\/","obj_id":"https:\/\/doi.org\/10.1177\/10778010222183107","source_token":"36c35e23-8757-4a9d-aacf-345e9b7eb50d","occurred_at":"2020-12-18T09:17:34Z","subj_id":"https:\/\/en.wikipedia.org\/api\/rest_v1\/page\/html\/Anita_Raj_(academic)\/994937561","id":"81776a81-b100-4cf7-be36-db37b304a6f4","evidence_record":"https:\/\/evidence.eventdata.crossref.org\/evidence\/20201218-wikipedia-01e50564-7987-41a3-b619-953eef0970dc","terms":"https:\/\/doi.org\/10.13003\/CED-terms-of-use","action":"add","subj":{"pid":"https:\/\/en.wikipedia.org\/wiki\/Anita_Raj_(academic)","url":"https:\/\/en.wikipedia.org\/w\/index.php?title=Anita_Raj_(academic)&oldid=994937561","title":"Anita Raj (academic)","work_type_id":"entry-encyclopedia","api-url":"https:\/\/en.wikipedia.org\/api\/rest_v1\/page\/html\/Anita_Raj_(academic)\/994937561"},"source_id":"wikipedia","obj":{"pid":"https:\/\/doi.org\/10.1177\/10778010222183107","url":"https:\/\/doi.org\/10.1177\/10778010222183107","method":"doi-literal","verification":"literal"},"timestamp":"2020-12-18T09:26:06Z","relation_type_id":"references"},{"license":"https:\/\/creativecommons.org\/publicdomain\/zero\/1.0\/","obj_id":"https:\/\/doi.org\/10.1177\/10778010222183107","source_token":"36c35e23-8757-4a9d-aacf-345e9b7eb50d","occurred_at":"2021-01-19T04:06:49Z","subj_id":"https:\/\/en.wikipedia.org\/api\/rest_v1\/page\/html\/Anita_Raj_(academic)\/1001313159","id":"a438e4eb-2cd4-44d5-ace5-e019931aa292","evidence_record":"https:\/\/evidence.eventdata.crossref.org\/evidence\/20210119-wikipedia-e12889e4-a73c-463d-b0af-86247e3c4262","terms":"https:\/\/doi.org\/10.13003\/CED-terms-of-use","action":"add","subj":{"pid":"https:\/\/en.wikipedia.org\/wiki\/Anita_Raj_(academic)","url":"https:\/\/en.wikipedia.org\/w\/index.php?title=Anita_Raj_(academic)&oldid=1001313159","title":"Anita Raj (academic)","work_type_id":"entry-encyclopedia","api-url":"https:\/\/en.wikipedia.org\/api\/rest_v1\/page\/html\/Anita_Raj_(academic)\/1001313159"},"source_id":"wikipedia","obj":{"pid":"https:\/\/doi.org\/10.1177\/10778010222183107","url":"https:\/\/doi.org\/10.1177\/10778010222183107","method":"doi-literal","verification":"literal"},"timestamp":"2021-01-19T04:18:03Z","relation_type_id":"references"}]}}