{"status":"ok","message-type":"event-list","message":{"next-cursor":"e8bf3158-02b7-4830-8147-b53a24190c7d","total-results":55,"items-per-page":1000,"events":[{"license":"https:\/\/creativecommons.org\/publicdomain\/zero\/1.0\/","terms":"https:\/\/doi.org\/10.13003\/CED-terms-of-use","updated_reason":"https:\/\/evidence.eventdata.crossref.org\/announcements\/2018-01-19T00-00-00Z-ED-15.json","updated":"edited","obj_id":"https:\/\/doi.org\/10.1177\/1354067x9952006","source_token":"36c35e23-8757-4a9d-aacf-345e9b7eb50d","occurred_at":"2017-08-27T14:32:04Z","subj_id":"https:\/\/en.wikipedia.org\/wiki\/Enactivism","id":"d1a783c7-debb-4f61-9df2-45f9cdc3845d","evidence_record":"https:\/\/evidence.eventdata.crossref.org\/evidence\/20170827-wikipedia-af551878-233a-46a2-9508-1322263dbb0d","terms":"https:\/\/doi.org\/10.13003\/CED-terms-of-use","action":"add","subj":{"pid":"https:\/\/en.wikipedia.org\/wiki\/Enactivism","url":"https:\/\/en.wikipedia.org\/w\/index.php?title=Enactivism&oldid=797513049","title":"Enactivism","api-url":"https:\/\/en.wikipedia.org\/api\/rest_v1\/page\/html\/Enactivism\/797513049"},"source_id":"wikipedia","obj":{"pid":"https:\/\/doi.org\/10.1177\/1354067x9952006","url":"https:\/\/doi.org\/10.1177\/1354067x9952006"},"timestamp":"2017-08-27T14:32:52Z","updated_date":"2018-01-31T17:30:00Z","relation_type_id":"references"},{"license":"https:\/\/creativecommons.org\/publicdomain\/zero\/1.0\/","terms":"https:\/\/doi.org\/10.13003\/CED-terms-of-use","updated_reason":"https:\/\/evidence.eventdata.crossref.org\/announcements\/2018-01-19T00-00-00Z-ED-15.json","updated":"edited","obj_id":"https:\/\/doi.org\/10.1177\/1354067x9952006","source_token":"36c35e23-8757-4a9d-aacf-345e9b7eb50d","occurred_at":"2017-08-28T12:52:31Z","subj_id":"https:\/\/en.wikipedia.org\/wiki\/Enactivism","id":"3556ed02-8296-450e-b962-d2c8d6963898","evidence_record":"https:\/\/evidence.eventdata.crossref.org\/evidence\/20170828-wikipedia-74c8f0a8-96d8-4337-8652-f8f519cc7f74","terms":"https:\/\/doi.org\/10.13003\/CED-terms-of-use","action":"add","subj":{"pid":"https:\/\/en.wikipedia.org\/wiki\/Enactivism","url":"https:\/\/en.wikipedia.org\/w\/index.php?title=Enactivism&oldid=797652733","title":"Enactivism","api-url":"https:\/\/en.wikipedia.org\/api\/rest_v1\/page\/html\/Enactivism\/797652733"},"source_id":"wikipedia","obj":{"pid":"https:\/\/doi.org\/10.1177\/1354067x9952006","url":"https:\/\/doi.org\/10.1177\/1354067x9952006"},"timestamp":"2017-08-28T12:53:28Z","updated_date":"2018-01-31T17:30:00Z","relation_type_id":"references"},{"license":"https:\/\/creativecommons.org\/publicdomain\/zero\/1.0\/","terms":"https:\/\/doi.org\/10.13003\/CED-terms-of-use","updated_reason":"https:\/\/evidence.eventdata.crossref.org\/announcements\/2018-01-19T00-00-00Z-ED-15.json","updated":"edited","obj_id":"https:\/\/doi.org\/10.1177\/1354067x9952006","source_token":"36c35e23-8757-4a9d-aacf-345e9b7eb50d","occurred_at":"2017-09-04T22:51:40Z","subj_id":"https:\/\/en.wikipedia.org\/wiki\/Enactivism","id":"36cd0ca6-3e6e-4f99-92ee-93b07d884b72","evidence_record":"https:\/\/evidence.eventdata.crossref.org\/evidence\/20170904-wikipedia-c65c2cda-311a-49e9-896e-df6782c0f878","terms":"https:\/\/doi.org\/10.13003\/CED-terms-of-use","action":"add","subj":{"pid":"https:\/\/en.wikipedia.org\/wiki\/Enactivism","url":"https:\/\/en.wikipedia.org\/w\/index.php?title=Enactivism&oldid=798977613","title":"Enactivism","api-url":"https:\/\/en.wikipedia.org\/api\/rest_v1\/page\/html\/Enactivism\/798977613"},"source_id":"wikipedia","obj":{"pid":"https:\/\/doi.org\/10.1177\/1354067x9952006","url":"https:\/\/doi.org\/10.1177\/1354067x9952006"},"timestamp":"2017-09-04T22:52:58Z","updated_date":"2018-01-31T17:30:00Z","relation_type_id":"references"},{"license":"https:\/\/creativecommons.org\/publicdomain\/zero\/1.0\/","terms":"https:\/\/doi.org\/10.13003\/CED-terms-of-use","updated_reason":"https:\/\/evidence.eventdata.crossref.org\/announcements\/2018-01-19T00-00-00Z-ED-15.json","updated":"edited","obj_id":"https:\/\/doi.org\/10.1177\/1354067x9952006","source_token":"36c35e23-8757-4a9d-aacf-345e9b7eb50d","occurred_at":"2017-09-04T22:55:10Z","subj_id":"https:\/\/en.wikipedia.org\/wiki\/Enactivism","id":"3fb8d996-e04f-442d-a889-ecfe2b33cbd3","evidence_record":"https:\/\/evidence.eventdata.crossref.org\/evidence\/20170904-wikipedia-eb50b672-2d8a-4ca2-ad97-ab40eae2a173","terms":"https:\/\/doi.org\/10.13003\/CED-terms-of-use","action":"add","subj":{"pid":"https:\/\/en.wikipedia.org\/wiki\/Enactivism","url":"https:\/\/en.wikipedia.org\/w\/index.php?title=Enactivism&oldid=798978011","title":"Enactivism","api-url":"https:\/\/en.wikipedia.org\/api\/rest_v1\/page\/html\/Enactivism\/798978011"},"source_id":"wikipedia","obj":{"pid":"https:\/\/doi.org\/10.1177\/1354067x9952006","url":"https:\/\/doi.org\/10.1177\/1354067x9952006"},"timestamp":"2017-09-04T22:55:56Z","updated_date":"2018-01-31T17:30:00Z","relation_type_id":"references"},{"license":"https:\/\/creativecommons.org\/publicdomain\/zero\/1.0\/","terms":"https:\/\/doi.org\/10.13003\/CED-terms-of-use","updated_reason":"https:\/\/evidence.eventdata.crossref.org\/announcements\/2018-01-19T00-00-00Z-ED-15.json","updated":"edited","obj_id":"https:\/\/doi.org\/10.1177\/1354067x9952006","source_token":"36c35e23-8757-4a9d-aacf-345e9b7eb50d","occurred_at":"2017-09-20T19:02:00Z","subj_id":"https:\/\/en.wikipedia.org\/wiki\/Enactivism","id":"06999936-2972-431d-9047-3582fb86de8d","evidence_record":"https:\/\/evidence.eventdata.crossref.org\/evidence\/20170920-wikipedia-8f73de8d-557b-464b-9e72-9e48aa13bf66","terms":"https:\/\/doi.org\/10.13003\/CED-terms-of-use","action":"add","subj":{"pid":"https:\/\/en.wikipedia.org\/wiki\/Enactivism","url":"https:\/\/en.wikipedia.org\/w\/index.php?title=Enactivism&oldid=801611373","title":"Enactivism","api-url":"https:\/\/en.wikipedia.org\/api\/rest_v1\/page\/html\/Enactivism\/801611373"},"source_id":"wikipedia","obj":{"pid":"https:\/\/doi.org\/10.1177\/1354067x9952006","url":"https:\/\/doi.org\/10.1177\/1354067x9952006"},"timestamp":"2017-09-20T19:03:09Z","updated_date":"2018-01-31T17:30:00Z","relation_type_id":"references"},{"license":"https:\/\/creativecommons.org\/publicdomain\/zero\/1.0\/","obj_id":"https:\/\/doi.org\/10.1177\/1354067x9952006","source_token":"36c35e23-8757-4a9d-aacf-345e9b7eb50d","occurred_at":"2017-10-27T09:04:15Z","subj_id":"https:\/\/en.wikipedia.org\/api\/rest_v1\/page\/html\/Enactivism\/807332920","id":"2ce7dad9-3e42-45cc-a759-7a2efa212751","evidence_record":"https:\/\/evidence.eventdata.crossref.org\/evidence\/20171027-wikipedia-4a6146de-6c70-4165-ad23-b0819342913c","terms":"https:\/\/doi.org\/10.13003\/CED-terms-of-use","action":"add","subj":{"pid":"https:\/\/en.wikipedia.org\/w\/index.php?title=Enactivism&oldid=807332920","url":"https:\/\/en.wikipedia.org\/wiki\/Enactivism","title":"Enactivism","api-url":"https:\/\/en.wikipedia.org\/api\/rest_v1\/page\/html\/Enactivism\/807332920"},"source_id":"wikipedia","obj":{"pid":"https:\/\/doi.org\/10.1177\/1354067x9952006","url":"https:\/\/doi.org\/10.1177\/1354067x9952006"},"timestamp":"2017-10-27T09:06:06Z","relation_type_id":"references"},{"license":"https:\/\/creativecommons.org\/publicdomain\/zero\/1.0\/","obj_id":"https:\/\/doi.org\/10.1177\/1354067x9952006","source_token":"36c35e23-8757-4a9d-aacf-345e9b7eb50d","occurred_at":"2017-10-27T09:16:31Z","subj_id":"https:\/\/en.wikipedia.org\/api\/rest_v1\/page\/html\/Enactivism\/807333976","id":"af2f78a4-6ef4-4e0e-8e21-2b79dd7284f0","evidence_record":"https:\/\/evidence.eventdata.crossref.org\/evidence\/20171027-wikipedia-5b434d42-8ae0-426c-80f8-97e5c97086a9","terms":"https:\/\/doi.org\/10.13003\/CED-terms-of-use","action":"add","subj":{"pid":"https:\/\/en.wikipedia.org\/w\/index.php?title=Enactivism&oldid=807333976","url":"https:\/\/en.wikipedia.org\/wiki\/Enactivism","title":"Enactivism","api-url":"https:\/\/en.wikipedia.org\/api\/rest_v1\/page\/html\/Enactivism\/807333976"},"source_id":"wikipedia","obj":{"pid":"https:\/\/doi.org\/10.1177\/1354067x9952006","url":"https:\/\/doi.org\/10.1177\/1354067x9952006"},"timestamp":"2017-10-27T09:18:21Z","relation_type_id":"references"},{"license":"https:\/\/creativecommons.org\/publicdomain\/zero\/1.0\/","obj_id":"https:\/\/doi.org\/10.1177\/1354067x9952006","source_token":"36c35e23-8757-4a9d-aacf-345e9b7eb50d","occurred_at":"2017-10-27T09:18:35Z","subj_id":"https:\/\/en.wikipedia.org\/api\/rest_v1\/page\/html\/Enactivism\/807334155","id":"2e1f3bab-9155-433b-823f-f19c19ef5b71","evidence_record":"https:\/\/evidence.eventdata.crossref.org\/evidence\/20171027-wikipedia-69e31b01-6889-45e7-b8c7-ec1fc8e05581","terms":"https:\/\/doi.org\/10.13003\/CED-terms-of-use","action":"add","subj":{"pid":"https:\/\/en.wikipedia.org\/w\/index.php?title=Enactivism&oldid=807334155","url":"https:\/\/en.wikipedia.org\/wiki\/Enactivism","title":"Enactivism","api-url":"https:\/\/en.wikipedia.org\/api\/rest_v1\/page\/html\/Enactivism\/807334155"},"source_id":"wikipedia","obj":{"pid":"https:\/\/doi.org\/10.1177\/1354067x9952006","url":"https:\/\/doi.org\/10.1177\/1354067x9952006"},"timestamp":"2017-10-27T09:19:26Z","relation_type_id":"references"},{"license":"https:\/\/creativecommons.org\/publicdomain\/zero\/1.0\/","obj_id":"https:\/\/doi.org\/10.1177\/1354067x9952006","source_token":"36c35e23-8757-4a9d-aacf-345e9b7eb50d","occurred_at":"2017-11-02T09:07:02Z","subj_id":"https:\/\/en.wikipedia.org\/api\/rest_v1\/page\/html\/Enactivism\/808343661","id":"0d96f955-6e84-4ee2-84de-871fc844e662","evidence_record":"https:\/\/evidence.eventdata.crossref.org\/evidence\/20171102-wikipedia-5d58c086-6aee-4abc-afdf-62c79ade3f93","terms":"https:\/\/doi.org\/10.13003\/CED-terms-of-use","action":"add","subj":{"pid":"https:\/\/en.wikipedia.org\/w\/index.php?title=Enactivism&oldid=808343661","url":"https:\/\/en.wikipedia.org\/wiki\/Enactivism","title":"Enactivism","api-url":"https:\/\/en.wikipedia.org\/api\/rest_v1\/page\/html\/Enactivism\/808343661"},"source_id":"wikipedia","obj":{"pid":"https:\/\/doi.org\/10.1177\/1354067x9952006","url":"https:\/\/doi.org\/10.1177\/1354067x9952006"},"timestamp":"2017-11-02T09:08:26Z","relation_type_id":"references"},{"license":"https:\/\/creativecommons.org\/publicdomain\/zero\/1.0\/","obj_id":"https:\/\/doi.org\/10.1177\/1354067x9952006","source_token":"36c35e23-8757-4a9d-aacf-345e9b7eb50d","occurred_at":"2017-11-29T18:30:09Z","subj_id":"https:\/\/en.wikipedia.org\/api\/rest_v1\/page\/html\/Enactivism\/812762061","id":"63228ab1-b880-4634-aa32-4e46f3abda1f","evidence_record":"https:\/\/evidence.eventdata.crossref.org\/evidence\/20171129-wikipedia-bee450e5-d6ad-427e-b4ac-5e36a8e43507","terms":"https:\/\/doi.org\/10.13003\/CED-terms-of-use","action":"add","subj":{"pid":"https:\/\/en.wikipedia.org\/w\/index.php?title=Enactivism&oldid=812762061","url":"https:\/\/en.wikipedia.org\/wiki\/Enactivism","title":"Enactivism","api-url":"https:\/\/en.wikipedia.org\/api\/rest_v1\/page\/html\/Enactivism\/812762061"},"source_id":"wikipedia","obj":{"pid":"https:\/\/doi.org\/10.1177\/1354067x9952006","url":"https:\/\/doi.org\/10.1177\/1354067x9952006"},"timestamp":"2018-01-06T01:48:32Z","relation_type_id":"references"},{"license":"https:\/\/creativecommons.org\/publicdomain\/zero\/1.0\/","obj_id":"https:\/\/doi.org\/10.1177\/1354067x9952006","source_token":"36c35e23-8757-4a9d-aacf-345e9b7eb50d","occurred_at":"2018-01-12T08:13:23Z","subj_id":"https:\/\/en.wikipedia.org\/api\/rest_v1\/page\/html\/Enactivism\/819966071","id":"77438da1-6087-4c27-b167-a180999567f8","evidence_record":"https:\/\/evidence.eventdata.crossref.org\/evidence\/20180112-wikipedia-9b432516-15c2-459a-9ab2-d1ef6a2cca46","terms":"https:\/\/doi.org\/10.13003\/CED-terms-of-use","action":"add","subj":{"pid":"https:\/\/en.wikipedia.org\/w\/index.php?title=Enactivism&oldid=819966071","url":"https:\/\/en.wikipedia.org\/wiki\/Enactivism","title":"Enactivism","api-url":"https:\/\/en.wikipedia.org\/api\/rest_v1\/page\/html\/Enactivism\/819966071"},"source_id":"wikipedia","obj":{"pid":"https:\/\/doi.org\/10.1177\/1354067x9952006","url":"https:\/\/doi.org\/10.1177\/1354067x9952006"},"timestamp":"2018-01-18T08:50:09Z","relation_type_id":"references"},{"license":"https:\/\/creativecommons.org\/publicdomain\/zero\/1.0\/","obj_id":"https:\/\/doi.org\/10.1177\/1354067x9952006","source_token":"36c35e23-8757-4a9d-aacf-345e9b7eb50d","occurred_at":"2018-05-19T20:35:48Z","subj_id":"https:\/\/en.wikipedia.org\/api\/rest_v1\/page\/html\/Enactivism\/842040659","id":"378e4a7c-10a6-4930-aab4-06b1d7ae43ba","evidence_record":"https:\/\/evidence.eventdata.crossref.org\/evidence\/20180519-wikipedia-d249b852-ff93-4de4-bfa9-cde6eeafd939","terms":"https:\/\/doi.org\/10.13003\/CED-terms-of-use","action":"add","subj":{"pid":"https:\/\/en.wikipedia.org\/wiki\/Enactivism","url":"https:\/\/en.wikipedia.org\/w\/index.php?title=Enactivism&oldid=842040659","title":"Enactivism","work_type_id":"entry-encyclopedia","api-url":"https:\/\/en.wikipedia.org\/api\/rest_v1\/page\/html\/Enactivism\/842040659"},"source_id":"wikipedia","obj":{"pid":"https:\/\/doi.org\/10.1177\/1354067x9952006","url":"https:\/\/doi.org\/10.1177\/1354067x9952006"},"timestamp":"2018-05-19T20:37:21Z","relation_type_id":"references"},{"license":"https:\/\/creativecommons.org\/publicdomain\/zero\/1.0\/","obj_id":"https:\/\/doi.org\/10.1177\/1354067x9952006","source_token":"36c35e23-8757-4a9d-aacf-345e9b7eb50d","occurred_at":"2018-10-25T20:27:29Z","subj_id":"https:\/\/en.wikipedia.org\/api\/rest_v1\/page\/html\/Enactivism\/865737009","id":"6dde0b3c-c5b2-4b8a-a1c9-e1c23f60346b","evidence_record":"https:\/\/evidence.eventdata.crossref.org\/evidence\/20181025-wikipedia-eadf96ba-186e-4e80-82f4-9007180640b5","terms":"https:\/\/doi.org\/10.13003\/CED-terms-of-use","action":"add","subj":{"pid":"https:\/\/en.wikipedia.org\/wiki\/Enactivism","url":"https:\/\/en.wikipedia.org\/w\/index.php?title=Enactivism&oldid=865737009","title":"Enactivism","work_type_id":"entry-encyclopedia","api-url":"https:\/\/en.wikipedia.org\/api\/rest_v1\/page\/html\/Enactivism\/865737009"},"source_id":"wikipedia","obj":{"pid":"https:\/\/doi.org\/10.1177\/1354067x9952006","url":"https:\/\/doi.org\/10.1177\/1354067x9952006","method":"doi-literal","verification":"literal"},"timestamp":"2018-10-25T20:29:58Z","relation_type_id":"references"},{"license":"https:\/\/creativecommons.org\/publicdomain\/zero\/1.0\/","obj_id":"https:\/\/doi.org\/10.1177\/1354067x9952006","source_token":"36c35e23-8757-4a9d-aacf-345e9b7eb50d","occurred_at":"2018-12-13T12:45:23Z","subj_id":"https:\/\/en.wikipedia.org\/api\/rest_v1\/page\/html\/Enactivism\/873487777","id":"a895fd84-54ca-4b8a-8c8e-456c8180fc4f","evidence_record":"https:\/\/evidence.eventdata.crossref.org\/evidence\/20181213-wikipedia-0bf1abe9-0662-4b41-8be1-74381b91d298","terms":"https:\/\/doi.org\/10.13003\/CED-terms-of-use","action":"add","subj":{"pid":"https:\/\/en.wikipedia.org\/wiki\/Enactivism","url":"https:\/\/en.wikipedia.org\/w\/index.php?title=Enactivism&oldid=873487777","title":"Enactivism","work_type_id":"entry-encyclopedia","api-url":"https:\/\/en.wikipedia.org\/api\/rest_v1\/page\/html\/Enactivism\/873487777"},"source_id":"wikipedia","obj":{"pid":"https:\/\/doi.org\/10.1177\/1354067x9952006","url":"https:\/\/doi.org\/10.1177\/1354067x9952006","method":"doi-literal","verification":"literal"},"timestamp":"2018-12-13T12:49:43Z","relation_type_id":"references"},{"license":"https:\/\/creativecommons.org\/publicdomain\/zero\/1.0\/","obj_id":"https:\/\/doi.org\/10.1177\/1354067x9952006","source_token":"36c35e23-8757-4a9d-aacf-345e9b7eb50d","occurred_at":"2019-01-27T23:23:34Z","subj_id":"https:\/\/en.wikipedia.org\/api\/rest_v1\/page\/html\/Enactivism\/880534536","id":"6124a3f5-cac3-4625-a37e-c552dbfa56b4","evidence_record":"https:\/\/evidence.eventdata.crossref.org\/evidence\/20190127-wikipedia-ca3d5671-264c-4e88-9ac7-023bc506472c","terms":"https:\/\/doi.org\/10.13003\/CED-terms-of-use","action":"add","subj":{"pid":"https:\/\/en.wikipedia.org\/wiki\/Enactivism","url":"https:\/\/en.wikipedia.org\/w\/index.php?title=Enactivism&oldid=880534536","title":"Enactivism","work_type_id":"entry-encyclopedia","api-url":"https:\/\/en.wikipedia.org\/api\/rest_v1\/page\/html\/Enactivism\/880534536"},"source_id":"wikipedia","obj":{"pid":"https:\/\/doi.org\/10.1177\/1354067x9952006","url":"https:\/\/doi.org\/10.1177\/1354067x9952006","method":"doi-literal","verification":"literal"},"timestamp":"2019-01-27T23:29:24Z","relation_type_id":"references"},{"license":"https:\/\/creativecommons.org\/publicdomain\/zero\/1.0\/","obj_id":"https:\/\/doi.org\/10.1177\/1354067x9952006","source_token":"36c35e23-8757-4a9d-aacf-345e9b7eb50d","occurred_at":"2019-01-28T15:43:22Z","subj_id":"https:\/\/en.wikipedia.org\/api\/rest_v1\/page\/html\/Enactivism\/880641652","id":"8355d195-e6a1-49fe-b65c-97695fe495f2","evidence_record":"https:\/\/evidence.eventdata.crossref.org\/evidence\/20190128-wikipedia-b323b27d-36b7-4b2e-87d0-48a070753363","terms":"https:\/\/doi.org\/10.13003\/CED-terms-of-use","action":"add","subj":{"pid":"https:\/\/en.wikipedia.org\/wiki\/Enactivism","url":"https:\/\/en.wikipedia.org\/w\/index.php?title=Enactivism&oldid=880641652","title":"Enactivism","work_type_id":"entry-encyclopedia","api-url":"https:\/\/en.wikipedia.org\/api\/rest_v1\/page\/html\/Enactivism\/880641652"},"source_id":"wikipedia","obj":{"pid":"https:\/\/doi.org\/10.1177\/1354067x9952006","url":"https:\/\/doi.org\/10.1177\/1354067x9952006","method":"doi-literal","verification":"literal"},"timestamp":"2019-01-28T15:48:00Z","relation_type_id":"references"},{"license":"https:\/\/creativecommons.org\/publicdomain\/zero\/1.0\/","obj_id":"https:\/\/doi.org\/10.1177\/1354067x9952006","source_token":"36c35e23-8757-4a9d-aacf-345e9b7eb50d","occurred_at":"2019-02-05T07:57:24Z","subj_id":"https:\/\/en.wikipedia.org\/api\/rest_v1\/page\/html\/Enactivism\/881859064","id":"1fec06ed-e510-4208-ab7e-73f547ad02e7","evidence_record":"https:\/\/evidence.eventdata.crossref.org\/evidence\/20190205-wikipedia-0c37ae38-4cb5-4a04-a149-ecc4305ab59c","terms":"https:\/\/doi.org\/10.13003\/CED-terms-of-use","action":"add","subj":{"pid":"https:\/\/en.wikipedia.org\/wiki\/Enactivism","url":"https:\/\/en.wikipedia.org\/w\/index.php?title=Enactivism&oldid=881859064","title":"Enactivism","work_type_id":"entry-encyclopedia","api-url":"https:\/\/en.wikipedia.org\/api\/rest_v1\/page\/html\/Enactivism\/881859064"},"source_id":"wikipedia","obj":{"pid":"https:\/\/doi.org\/10.1177\/1354067x9952006","url":"https:\/\/doi.org\/10.1177\/1354067x9952006","method":"doi-literal","verification":"literal"},"timestamp":"2019-02-05T08:08:42Z","relation_type_id":"references"},{"license":"https:\/\/creativecommons.org\/publicdomain\/zero\/1.0\/","obj_id":"https:\/\/doi.org\/10.1177\/1354067x9952006","source_token":"36c35e23-8757-4a9d-aacf-345e9b7eb50d","occurred_at":"2019-02-17T21:46:33Z","subj_id":"https:\/\/en.wikipedia.org\/api\/rest_v1\/page\/html\/Enactivism\/883826896","id":"81a71ee9-ce74-40fc-9c8a-3383642c3610","evidence_record":"https:\/\/evidence.eventdata.crossref.org\/evidence\/20190217-wikipedia-aa86706b-9c7a-4806-94c6-ea1159ff8225","terms":"https:\/\/doi.org\/10.13003\/CED-terms-of-use","action":"add","subj":{"pid":"https:\/\/en.wikipedia.org\/wiki\/Enactivism","url":"https:\/\/en.wikipedia.org\/w\/index.php?title=Enactivism&oldid=883826896","title":"Enactivism","work_type_id":"entry-encyclopedia","api-url":"https:\/\/en.wikipedia.org\/api\/rest_v1\/page\/html\/Enactivism\/883826896"},"source_id":"wikipedia","obj":{"pid":"https:\/\/doi.org\/10.1177\/1354067x9952006","url":"https:\/\/doi.org\/10.1177\/1354067x9952006","method":"doi-literal","verification":"literal"},"timestamp":"2019-02-17T21:50:03Z","relation_type_id":"references"},{"license":"https:\/\/creativecommons.org\/publicdomain\/zero\/1.0\/","obj_id":"https:\/\/doi.org\/10.1177\/1354067x9952006","source_token":"36c35e23-8757-4a9d-aacf-345e9b7eb50d","occurred_at":"2019-02-18T03:05:57Z","subj_id":"https:\/\/en.wikipedia.org\/api\/rest_v1\/page\/html\/Enactivism\/883864894","id":"35746572-7b41-4874-8fc7-7a222ca87517","evidence_record":"https:\/\/evidence.eventdata.crossref.org\/evidence\/20190218-wikipedia-62c17618-a2e9-4195-9a31-9bf3f9f09aa9","terms":"https:\/\/doi.org\/10.13003\/CED-terms-of-use","action":"add","subj":{"pid":"https:\/\/en.wikipedia.org\/wiki\/Enactivism","url":"https:\/\/en.wikipedia.org\/w\/index.php?title=Enactivism&oldid=883864894","title":"Enactivism","work_type_id":"entry-encyclopedia","api-url":"https:\/\/en.wikipedia.org\/api\/rest_v1\/page\/html\/Enactivism\/883864894"},"source_id":"wikipedia","obj":{"pid":"https:\/\/doi.org\/10.1177\/1354067x9952006","url":"https:\/\/doi.org\/10.1177\/1354067x9952006","method":"doi-literal","verification":"literal"},"timestamp":"2019-02-18T03:12:08Z","relation_type_id":"references"},{"license":"https:\/\/creativecommons.org\/publicdomain\/zero\/1.0\/","obj_id":"https:\/\/doi.org\/10.1177\/1354067x9952006","source_token":"36c35e23-8757-4a9d-aacf-345e9b7eb50d","occurred_at":"2019-02-18T04:09:18Z","subj_id":"https:\/\/en.wikipedia.org\/api\/rest_v1\/page\/html\/Enactivism\/883872666","id":"966fa331-9607-4854-9626-59ed65bf335b","evidence_record":"https:\/\/evidence.eventdata.crossref.org\/evidence\/20190218-wikipedia-888c192e-0252-4b77-8f9f-ae598d83f930","terms":"https:\/\/doi.org\/10.13003\/CED-terms-of-use","action":"add","subj":{"pid":"https:\/\/en.wikipedia.org\/wiki\/Enactivism","url":"https:\/\/en.wikipedia.org\/w\/index.php?title=Enactivism&oldid=883872666","title":"Enactivism","work_type_id":"entry-encyclopedia","api-url":"https:\/\/en.wikipedia.org\/api\/rest_v1\/page\/html\/Enactivism\/883872666"},"source_id":"wikipedia","obj":{"pid":"https:\/\/doi.org\/10.1177\/1354067x9952006","url":"https:\/\/doi.org\/10.1177\/1354067x9952006","method":"doi-literal","verification":"literal"},"timestamp":"2019-02-18T04:20:41Z","relation_type_id":"references"},{"license":"https:\/\/creativecommons.org\/publicdomain\/zero\/1.0\/","obj_id":"https:\/\/doi.org\/10.1177\/1354067x9952006","source_token":"36c35e23-8757-4a9d-aacf-345e9b7eb50d","occurred_at":"2019-03-11T06:06:05Z","subj_id":"https:\/\/en.wikipedia.org\/api\/rest_v1\/page\/html\/Enactivism\/887202627","id":"86645150-c9b1-4ea4-92cf-4554be6db989","evidence_record":"https:\/\/evidence.eventdata.crossref.org\/evidence\/20190311-wikipedia-a40b62aa-9133-44ce-a904-ca4d2ce8ba48","terms":"https:\/\/doi.org\/10.13003\/CED-terms-of-use","action":"add","subj":{"pid":"https:\/\/en.wikipedia.org\/wiki\/Enactivism","url":"https:\/\/en.wikipedia.org\/w\/index.php?title=Enactivism&oldid=887202627","title":"Enactivism","work_type_id":"entry-encyclopedia","api-url":"https:\/\/en.wikipedia.org\/api\/rest_v1\/page\/html\/Enactivism\/887202627"},"source_id":"wikipedia","obj":{"pid":"https:\/\/doi.org\/10.1177\/1354067x9952006","url":"https:\/\/doi.org\/10.1177\/1354067x9952006","method":"doi-literal","verification":"literal"},"timestamp":"2019-03-11T06:10:05Z","relation_type_id":"references"},{"license":"https:\/\/creativecommons.org\/publicdomain\/zero\/1.0\/","obj_id":"https:\/\/doi.org\/10.1177\/1354067x9952006","source_token":"36c35e23-8757-4a9d-aacf-345e9b7eb50d","occurred_at":"2019-06-25T04:48:13Z","subj_id":"https:\/\/en.wikipedia.org\/api\/rest_v1\/page\/html\/Enactivism\/903344514","id":"1baca145-6a3c-40ee-b058-6a33704b9a42","evidence_record":"https:\/\/evidence.eventdata.crossref.org\/evidence\/20190625-wikipedia-2aba09ca-5ba5-4dde-8ecf-8e1ca31608ac","terms":"https:\/\/doi.org\/10.13003\/CED-terms-of-use","action":"add","subj":{"pid":"https:\/\/en.wikipedia.org\/wiki\/Enactivism","url":"https:\/\/en.wikipedia.org\/w\/index.php?title=Enactivism&oldid=903344514","title":"Enactivism","work_type_id":"entry-encyclopedia","api-url":"https:\/\/en.wikipedia.org\/api\/rest_v1\/page\/html\/Enactivism\/903344514"},"source_id":"wikipedia","obj":{"pid":"https:\/\/doi.org\/10.1177\/1354067x9952006","url":"https:\/\/doi.org\/10.1177\/1354067x9952006","method":"doi-literal","verification":"literal"},"timestamp":"2019-06-25T04:56:36Z","relation_type_id":"references"},{"license":"https:\/\/doi.org\/10.13003\/CED-terms-of-use","obj_id":"https:\/\/doi.org\/10.1177\/1354067X9952006","source_token":"8676e950-8ac5-4074-8ac3-c0a18ada7e99","occurred_at":"2012-11-16T00:00:00Z","subj_id":"https:\/\/doi.org\/10.1007\/s12124-012-9221-z","id":"54b7f7d8-db99-4a4d-a405-41849ce56b55","terms":"https:\/\/doi.org\/10.13003\/CED-terms-of-use","message_action":"create","source_id":"crossref","timestamp":"2019-07-24T20:07:45Z","relation_type_id":"references"},{"license":"https:\/\/creativecommons.org\/publicdomain\/zero\/1.0\/","obj_id":"https:\/\/doi.org\/10.1177\/1354067x9952006","source_token":"36c35e23-8757-4a9d-aacf-345e9b7eb50d","occurred_at":"2019-08-08T04:39:45Z","subj_id":"https:\/\/en.wikipedia.org\/api\/rest_v1\/page\/html\/Enactivism\/909870919","id":"aaad9804-e172-47c0-aef3-e8593962df86","evidence_record":"https:\/\/evidence.eventdata.crossref.org\/evidence\/20190808-wikipedia-e4e2b3d8-d727-4cbd-a80b-5480a416a80e","terms":"https:\/\/doi.org\/10.13003\/CED-terms-of-use","action":"add","subj":{"pid":"https:\/\/en.wikipedia.org\/wiki\/Enactivism","url":"https:\/\/en.wikipedia.org\/w\/index.php?title=Enactivism&oldid=909870919","title":"Enactivism","work_type_id":"entry-encyclopedia","api-url":"https:\/\/en.wikipedia.org\/api\/rest_v1\/page\/html\/Enactivism\/909870919"},"source_id":"wikipedia","obj":{"pid":"https:\/\/doi.org\/10.1177\/1354067x9952006","url":"https:\/\/doi.org\/10.1177\/1354067x9952006","method":"doi-literal","verification":"literal"},"timestamp":"2019-08-10T10:33:16Z","relation_type_id":"references"},{"license":"https:\/\/creativecommons.org\/publicdomain\/zero\/1.0\/","obj_id":"https:\/\/doi.org\/10.1177\/1354067x9952006","source_token":"36c35e23-8757-4a9d-aacf-345e9b7eb50d","occurred_at":"2019-08-21T00:13:46Z","subj_id":"https:\/\/en.wikipedia.org\/api\/rest_v1\/page\/html\/Enactivism\/911764562","id":"73f68b6f-3f98-4ad6-a132-2276b9a80d27","evidence_record":"https:\/\/evidence.eventdata.crossref.org\/evidence\/20190821-wikipedia-a9fe22e1-5622-4f85-a260-f9476bf35f2a","terms":"https:\/\/doi.org\/10.13003\/CED-terms-of-use","action":"add","subj":{"pid":"https:\/\/en.wikipedia.org\/wiki\/Enactivism","url":"https:\/\/en.wikipedia.org\/w\/index.php?title=Enactivism&oldid=911764562","title":"Enactivism","work_type_id":"entry-encyclopedia","api-url":"https:\/\/en.wikipedia.org\/api\/rest_v1\/page\/html\/Enactivism\/911764562"},"source_id":"wikipedia","obj":{"pid":"https:\/\/doi.org\/10.1177\/1354067x9952006","url":"https:\/\/doi.org\/10.1177\/1354067x9952006","method":"doi-literal","verification":"literal"},"timestamp":"2019-08-21T00:24:03Z","relation_type_id":"references"},{"license":"https:\/\/creativecommons.org\/publicdomain\/zero\/1.0\/","obj_id":"https:\/\/doi.org\/10.1177\/1354067x9952006","source_token":"36c35e23-8757-4a9d-aacf-345e9b7eb50d","occurred_at":"2019-09-08T04:22:08Z","subj_id":"https:\/\/en.wikipedia.org\/api\/rest_v1\/page\/html\/Enactivism\/914568404","id":"7354e968-540b-473a-b1bb-23f90850bba4","evidence_record":"https:\/\/evidence.eventdata.crossref.org\/evidence\/20190908-wikipedia-ca7d580f-032f-4a32-89f7-2e2d367b8e30","terms":"https:\/\/doi.org\/10.13003\/CED-terms-of-use","action":"add","subj":{"pid":"https:\/\/en.wikipedia.org\/wiki\/Enactivism","url":"https:\/\/en.wikipedia.org\/w\/index.php?title=Enactivism&oldid=914568404","title":"Enactivism","work_type_id":"entry-encyclopedia","api-url":"https:\/\/en.wikipedia.org\/api\/rest_v1\/page\/html\/Enactivism\/914568404"},"source_id":"wikipedia","obj":{"pid":"https:\/\/doi.org\/10.1177\/1354067x9952006","url":"https:\/\/doi.org\/10.1177\/1354067x9952006","method":"doi-literal","verification":"literal"},"timestamp":"2019-09-08T04:39:51Z","relation_type_id":"references"},{"license":"https:\/\/creativecommons.org\/publicdomain\/zero\/1.0\/","obj_id":"https:\/\/doi.org\/10.1177\/1354067x9952006","source_token":"36c35e23-8757-4a9d-aacf-345e9b7eb50d","occurred_at":"2019-09-19T21:16:08Z","subj_id":"https:\/\/en.wikipedia.org\/api\/rest_v1\/page\/html\/Enactivism\/916633079","id":"94886435-c654-4bfa-ad6a-375d2392aab9","evidence_record":"https:\/\/evidence.eventdata.crossref.org\/evidence\/20190919-wikipedia-cf20e309-abfc-477c-87fe-251ccec4a632","terms":"https:\/\/doi.org\/10.13003\/CED-terms-of-use","action":"add","subj":{"pid":"https:\/\/en.wikipedia.org\/wiki\/Enactivism","url":"https:\/\/en.wikipedia.org\/w\/index.php?title=Enactivism&oldid=916633079","title":"Enactivism","work_type_id":"entry-encyclopedia","api-url":"https:\/\/en.wikipedia.org\/api\/rest_v1\/page\/html\/Enactivism\/916633079"},"source_id":"wikipedia","obj":{"pid":"https:\/\/doi.org\/10.1177\/1354067x9952006","url":"https:\/\/doi.org\/10.1177\/1354067x9952006","method":"doi-literal","verification":"literal"},"timestamp":"2019-09-19T21:22:43Z","relation_type_id":"references"},{"license":"https:\/\/creativecommons.org\/publicdomain\/zero\/1.0\/","obj_id":"https:\/\/doi.org\/10.1177\/1354067x9952006","source_token":"36c35e23-8757-4a9d-aacf-345e9b7eb50d","occurred_at":"2019-11-10T07:27:18Z","subj_id":"https:\/\/en.wikipedia.org\/api\/rest_v1\/page\/html\/Enactivism\/925462134","id":"e1578206-e518-4348-a310-3fcf2e05d6f8","evidence_record":"https:\/\/evidence.eventdata.crossref.org\/evidence\/20191110-wikipedia-522e376c-2609-450f-a99d-2c6344eb3a00","terms":"https:\/\/doi.org\/10.13003\/CED-terms-of-use","action":"add","subj":{"pid":"https:\/\/en.wikipedia.org\/wiki\/Enactivism","url":"https:\/\/en.wikipedia.org\/w\/index.php?title=Enactivism&oldid=925462134","title":"Enactivism","work_type_id":"entry-encyclopedia","api-url":"https:\/\/en.wikipedia.org\/api\/rest_v1\/page\/html\/Enactivism\/925462134"},"source_id":"wikipedia","obj":{"pid":"https:\/\/doi.org\/10.1177\/1354067x9952006","url":"https:\/\/doi.org\/10.1177\/1354067x9952006","method":"doi-literal","verification":"literal"},"timestamp":"2019-11-10T08:20:49Z","relation_type_id":"references"},{"license":"https:\/\/creativecommons.org\/publicdomain\/zero\/1.0\/","obj_id":"https:\/\/doi.org\/10.1177\/1354067x9952006","source_token":"36c35e23-8757-4a9d-aacf-345e9b7eb50d","occurred_at":"2019-12-07T05:00:17Z","subj_id":"https:\/\/en.wikipedia.org\/api\/rest_v1\/page\/html\/Enactivism\/929639577","id":"6a6fc12a-0589-44b4-9aa6-90a95f785c66","evidence_record":"https:\/\/evidence.eventdata.crossref.org\/evidence\/20191207-wikipedia-bcf3ce93-e896-40e0-9c6c-1810118b156a","terms":"https:\/\/doi.org\/10.13003\/CED-terms-of-use","action":"add","subj":{"pid":"https:\/\/en.wikipedia.org\/wiki\/Enactivism","url":"https:\/\/en.wikipedia.org\/w\/index.php?title=Enactivism&oldid=929639577","title":"Enactivism","work_type_id":"entry-encyclopedia","api-url":"https:\/\/en.wikipedia.org\/api\/rest_v1\/page\/html\/Enactivism\/929639577"},"source_id":"wikipedia","obj":{"pid":"https:\/\/doi.org\/10.1177\/1354067x9952006","url":"https:\/\/doi.org\/10.1177\/1354067x9952006","method":"doi-literal","verification":"literal"},"timestamp":"2019-12-07T07:02:33Z","relation_type_id":"references"},{"license":"https:\/\/creativecommons.org\/publicdomain\/zero\/1.0\/","obj_id":"https:\/\/doi.org\/10.1177\/1354067x9952006","source_token":"36c35e23-8757-4a9d-aacf-345e9b7eb50d","occurred_at":"2019-11-10T07:27:18Z","subj_id":"https:\/\/en.wikipedia.org\/api\/rest_v1\/page\/html\/Enactivism\/925462134","id":"ea19d8d2-3e66-4904-b55b-afbf833daeef","evidence_record":"https:\/\/evidence.eventdata.crossref.org\/evidence\/20191208-wikipedia-3f57fa45-ce53-4171-82a4-d0ee98b524c3","terms":"https:\/\/doi.org\/10.13003\/CED-terms-of-use","action":"add","subj":{"pid":"https:\/\/en.wikipedia.org\/wiki\/Enactivism","url":"https:\/\/en.wikipedia.org\/w\/index.php?title=Enactivism&oldid=925462134","title":"Enactivism","work_type_id":"entry-encyclopedia","api-url":"https:\/\/en.wikipedia.org\/api\/rest_v1\/page\/html\/Enactivism\/925462134"},"source_id":"wikipedia","obj":{"pid":"https:\/\/doi.org\/10.1177\/1354067x9952006","url":"https:\/\/doi.org\/10.1177\/1354067x9952006","method":"doi-literal","verification":"literal"},"timestamp":"2019-12-09T05:09:41Z","relation_type_id":"references"},{"license":"https:\/\/creativecommons.org\/publicdomain\/zero\/1.0\/","obj_id":"https:\/\/doi.org\/10.1177\/1354067x9952006","source_token":"36c35e23-8757-4a9d-aacf-345e9b7eb50d","occurred_at":"2019-12-07T05:00:17Z","subj_id":"https:\/\/en.wikipedia.org\/api\/rest_v1\/page\/html\/Enactivism\/929639577","id":"7e01d2d6-3575-478a-8c3e-e601d7d0416a","evidence_record":"https:\/\/evidence.eventdata.crossref.org\/evidence\/20191208-wikipedia-d95e0f28-9bb5-4c2c-ae89-83b4b5270937","terms":"https:\/\/doi.org\/10.13003\/CED-terms-of-use","action":"add","subj":{"pid":"https:\/\/en.wikipedia.org\/wiki\/Enactivism","url":"https:\/\/en.wikipedia.org\/w\/index.php?title=Enactivism&oldid=929639577","title":"Enactivism","work_type_id":"entry-encyclopedia","api-url":"https:\/\/en.wikipedia.org\/api\/rest_v1\/page\/html\/Enactivism\/929639577"},"source_id":"wikipedia","obj":{"pid":"https:\/\/doi.org\/10.1177\/1354067x9952006","url":"https:\/\/doi.org\/10.1177\/1354067x9952006","method":"doi-literal","verification":"literal"},"timestamp":"2019-12-15T01:12:41Z","relation_type_id":"references"},{"license":"https:\/\/creativecommons.org\/publicdomain\/zero\/1.0\/","obj_id":"https:\/\/doi.org\/10.1177\/1354067x9952006","source_token":"36c35e23-8757-4a9d-aacf-345e9b7eb50d","occurred_at":"2019-12-18T21:52:40Z","subj_id":"https:\/\/en.wikipedia.org\/api\/rest_v1\/page\/html\/Enactivism\/931432928","id":"5eacbac5-ce08-414d-bd05-7a190dd087e6","evidence_record":"https:\/\/evidence.eventdata.crossref.org\/evidence\/20191218-wikipedia-b74b99d2-00bf-42bf-a921-ef61f9beead2","terms":"https:\/\/doi.org\/10.13003\/CED-terms-of-use","action":"add","subj":{"pid":"https:\/\/en.wikipedia.org\/wiki\/Enactivism","url":"https:\/\/en.wikipedia.org\/w\/index.php?title=Enactivism&oldid=931432928","title":"Enactivism","work_type_id":"entry-encyclopedia","api-url":"https:\/\/en.wikipedia.org\/api\/rest_v1\/page\/html\/Enactivism\/931432928"},"source_id":"wikipedia","obj":{"pid":"https:\/\/doi.org\/10.1177\/1354067x9952006","url":"https:\/\/doi.org\/10.1177\/1354067x9952006","method":"doi-literal","verification":"literal"},"timestamp":"2019-12-20T01:30:30Z","relation_type_id":"references"},{"license":"https:\/\/creativecommons.org\/publicdomain\/zero\/1.0\/","obj_id":"https:\/\/doi.org\/10.1177\/1354067x9952006","source_token":"36c35e23-8757-4a9d-aacf-345e9b7eb50d","occurred_at":"2020-09-01T01:54:42Z","subj_id":"https:\/\/en.wikipedia.org\/api\/rest_v1\/page\/html\/Enactivism\/976074671","id":"9ac8bde4-c555-48e8-a310-446522a0ab1b","evidence_record":"https:\/\/evidence.eventdata.crossref.org\/evidence\/20200901-wikipedia-5f7174d3-aad5-486f-99cf-ed417a36bc39","terms":"https:\/\/doi.org\/10.13003\/CED-terms-of-use","action":"add","subj":{"pid":"https:\/\/en.wikipedia.org\/wiki\/Enactivism","url":"https:\/\/en.wikipedia.org\/w\/index.php?title=Enactivism&oldid=976074671","title":"Enactivism","work_type_id":"entry-encyclopedia","api-url":"https:\/\/en.wikipedia.org\/api\/rest_v1\/page\/html\/Enactivism\/976074671"},"source_id":"wikipedia","obj":{"pid":"https:\/\/doi.org\/10.1177\/1354067x9952006","url":"https:\/\/doi.org\/10.1177\/1354067x9952006","method":"doi-literal","verification":"literal"},"timestamp":"2020-09-06T19:39:26Z","relation_type_id":"references"},{"license":"https:\/\/creativecommons.org\/publicdomain\/zero\/1.0\/","obj_id":"https:\/\/doi.org\/10.1177\/1354067x9952006","source_token":"36c35e23-8757-4a9d-aacf-345e9b7eb50d","occurred_at":"2020-04-02T23:54:40Z","subj_id":"https:\/\/en.wikipedia.org\/api\/rest_v1\/page\/html\/Enactivism\/948777627","id":"272b4f48-bbcc-4e1d-bd94-a03603e920e8","evidence_record":"https:\/\/evidence.eventdata.crossref.org\/evidence\/20200402-wikipedia-0287f42f-c482-439a-aaa4-804cfaf3b948","terms":"https:\/\/doi.org\/10.13003\/CED-terms-of-use","action":"add","subj":{"pid":"https:\/\/en.wikipedia.org\/wiki\/Enactivism","url":"https:\/\/en.wikipedia.org\/w\/index.php?title=Enactivism&oldid=948777627","title":"Enactivism","work_type_id":"entry-encyclopedia","api-url":"https:\/\/en.wikipedia.org\/api\/rest_v1\/page\/html\/Enactivism\/948777627"},"source_id":"wikipedia","obj":{"pid":"https:\/\/doi.org\/10.1177\/1354067x9952006","url":"https:\/\/doi.org\/10.1177\/1354067x9952006","method":"doi-literal","verification":"literal"},"timestamp":"2020-10-14T01:48:04Z","relation_type_id":"references"},{"license":"https:\/\/creativecommons.org\/publicdomain\/zero\/1.0\/","obj_id":"https:\/\/doi.org\/10.1177\/1354067x9952006","source_token":"36c35e23-8757-4a9d-aacf-345e9b7eb50d","occurred_at":"2020-05-11T17:40:03Z","subj_id":"https:\/\/en.wikipedia.org\/api\/rest_v1\/page\/html\/Enactivism\/956133321","id":"c4b247cb-766e-451f-ae5f-b0c5df5c64bd","evidence_record":"https:\/\/evidence.eventdata.crossref.org\/evidence\/20200511-wikipedia-afe9dfc3-34fd-4cec-8bb0-5681b1cda2b5","terms":"https:\/\/doi.org\/10.13003\/CED-terms-of-use","action":"add","subj":{"pid":"https:\/\/en.wikipedia.org\/wiki\/Enactivism","url":"https:\/\/en.wikipedia.org\/w\/index.php?title=Enactivism&oldid=956133321","title":"Enactivism","work_type_id":"entry-encyclopedia","api-url":"https:\/\/en.wikipedia.org\/api\/rest_v1\/page\/html\/Enactivism\/956133321"},"source_id":"wikipedia","obj":{"pid":"https:\/\/doi.org\/10.1177\/1354067x9952006","url":"https:\/\/doi.org\/10.1177\/1354067x9952006","method":"doi-literal","verification":"literal"},"timestamp":"2020-10-14T21:37:23Z","relation_type_id":"references"},{"license":"https:\/\/creativecommons.org\/publicdomain\/zero\/1.0\/","obj_id":"https:\/\/doi.org\/10.1177\/1354067x9952006","source_token":"36c35e23-8757-4a9d-aacf-345e9b7eb50d","occurred_at":"2020-07-18T10:55:04Z","subj_id":"https:\/\/en.wikipedia.org\/api\/rest_v1\/page\/html\/Enactivism\/968276538","id":"f459de0d-9003-45f1-853b-4ee2811c353b","evidence_record":"https:\/\/evidence.eventdata.crossref.org\/evidence\/20200718-wikipedia-9775a12f-6dd8-4cdc-a648-31bb064b8456","terms":"https:\/\/doi.org\/10.13003\/CED-terms-of-use","action":"add","subj":{"pid":"https:\/\/en.wikipedia.org\/wiki\/Enactivism","url":"https:\/\/en.wikipedia.org\/w\/index.php?title=Enactivism&oldid=968276538","title":"Enactivism","work_type_id":"entry-encyclopedia","api-url":"https:\/\/en.wikipedia.org\/api\/rest_v1\/page\/html\/Enactivism\/968276538"},"source_id":"wikipedia","obj":{"pid":"https:\/\/doi.org\/10.1177\/1354067x9952006","url":"https:\/\/doi.org\/10.1177\/1354067x9952006","method":"doi-literal","verification":"literal"},"timestamp":"2020-10-16T10:01:59Z","relation_type_id":"references"},{"license":"https:\/\/creativecommons.org\/publicdomain\/zero\/1.0\/","obj_id":"https:\/\/doi.org\/10.1177\/1354067x9952006","source_token":"36c35e23-8757-4a9d-aacf-345e9b7eb50d","occurred_at":"2020-07-18T10:55:04Z","subj_id":"https:\/\/en.wikipedia.org\/api\/rest_v1\/page\/html\/Enactivism\/968276538","id":"a96a26ae-fea7-48af-aea3-6ddb0af69143","evidence_record":"https:\/\/evidence.eventdata.crossref.org\/evidence\/20200718-wikipedia-b20ed7e7-c6ed-4a45-8111-eddf8960e31f","terms":"https:\/\/doi.org\/10.13003\/CED-terms-of-use","action":"add","subj":{"pid":"https:\/\/en.wikipedia.org\/wiki\/Enactivism","url":"https:\/\/en.wikipedia.org\/w\/index.php?title=Enactivism&oldid=968276538","title":"Enactivism","work_type_id":"entry-encyclopedia","api-url":"https:\/\/en.wikipedia.org\/api\/rest_v1\/page\/html\/Enactivism\/968276538"},"source_id":"wikipedia","obj":{"pid":"https:\/\/doi.org\/10.1177\/1354067x9952006","url":"https:\/\/doi.org\/10.1177\/1354067x9952006","method":"doi-literal","verification":"literal"},"timestamp":"2020-10-16T10:30:25Z","relation_type_id":"references"},{"license":"https:\/\/creativecommons.org\/publicdomain\/zero\/1.0\/","obj_id":"https:\/\/doi.org\/10.1177\/1354067x9952006","source_token":"36c35e23-8757-4a9d-aacf-345e9b7eb50d","occurred_at":"2020-10-25T04:58:03Z","subj_id":"https:\/\/en.wikipedia.org\/api\/rest_v1\/page\/html\/Enactivism\/985301394","id":"0471cd18-e6e8-4af8-b539-4af433bf33ee","evidence_record":"https:\/\/evidence.eventdata.crossref.org\/evidence\/20201025-wikipedia-f87d3626-058f-43f0-a2cb-da0fad4d74d3","terms":"https:\/\/doi.org\/10.13003\/CED-terms-of-use","action":"add","subj":{"pid":"https:\/\/en.wikipedia.org\/wiki\/Enactivism","url":"https:\/\/en.wikipedia.org\/w\/index.php?title=Enactivism&oldid=985301394","title":"Enactivism","work_type_id":"entry-encyclopedia","api-url":"https:\/\/en.wikipedia.org\/api\/rest_v1\/page\/html\/Enactivism\/985301394"},"source_id":"wikipedia","obj":{"pid":"https:\/\/doi.org\/10.1177\/1354067x9952006","url":"https:\/\/doi.org\/10.1177\/1354067x9952006","method":"doi-literal","verification":"literal"},"timestamp":"2020-10-25T05:02:06Z","relation_type_id":"references"},{"license":"https:\/\/creativecommons.org\/publicdomain\/zero\/1.0\/","obj_id":"https:\/\/doi.org\/10.1177\/1354067x9952006","source_token":"36c35e23-8757-4a9d-aacf-345e9b7eb50d","occurred_at":"2020-12-03T23:52:40Z","subj_id":"https:\/\/en.wikipedia.org\/api\/rest_v1\/page\/html\/Enactivism\/992189137","id":"d4dac0ad-ba1d-45a4-852d-8f95f9d9151d","evidence_record":"https:\/\/evidence.eventdata.crossref.org\/evidence\/20201203-wikipedia-d2c21045-4b7b-42ad-9e8c-4350e5a903cb","terms":"https:\/\/doi.org\/10.13003\/CED-terms-of-use","action":"add","subj":{"pid":"https:\/\/en.wikipedia.org\/wiki\/Enactivism","url":"https:\/\/en.wikipedia.org\/w\/index.php?title=Enactivism&oldid=992189137","title":"Enactivism","work_type_id":"entry-encyclopedia","api-url":"https:\/\/en.wikipedia.org\/api\/rest_v1\/page\/html\/Enactivism\/992189137"},"source_id":"wikipedia","obj":{"pid":"https:\/\/doi.org\/10.1177\/1354067x9952006","url":"https:\/\/doi.org\/10.1177\/1354067x9952006","method":"doi-literal","verification":"literal"},"timestamp":"2020-12-04T00:38:56Z","relation_type_id":"references"},{"license":"https:\/\/creativecommons.org\/publicdomain\/zero\/1.0\/","obj_id":"https:\/\/doi.org\/10.1177\/1354067x9952006","source_token":"36c35e23-8757-4a9d-aacf-345e9b7eb50d","occurred_at":"2020-12-12T03:09:48Z","subj_id":"https:\/\/en.wikipedia.org\/api\/rest_v1\/page\/html\/Enactivism\/993719834","id":"361879aa-1855-4618-a8b8-c6ce1434242b","evidence_record":"https:\/\/evidence.eventdata.crossref.org\/evidence\/20201212-wikipedia-3c4f21b1-0a1f-49ea-90ff-d24ac85375c3","terms":"https:\/\/doi.org\/10.13003\/CED-terms-of-use","action":"add","subj":{"pid":"https:\/\/en.wikipedia.org\/wiki\/Enactivism","url":"https:\/\/en.wikipedia.org\/w\/index.php?title=Enactivism&oldid=993719834","title":"Enactivism","work_type_id":"entry-encyclopedia","api-url":"https:\/\/en.wikipedia.org\/api\/rest_v1\/page\/html\/Enactivism\/993719834"},"source_id":"wikipedia","obj":{"pid":"https:\/\/doi.org\/10.1177\/1354067x9952006","url":"https:\/\/doi.org\/10.1177\/1354067x9952006","method":"doi-literal","verification":"literal"},"timestamp":"2020-12-12T03:16:53Z","relation_type_id":"references"},{"license":"https:\/\/creativecommons.org\/publicdomain\/zero\/1.0\/","obj_id":"https:\/\/doi.org\/10.1177\/1354067x9952006","source_token":"36c35e23-8757-4a9d-aacf-345e9b7eb50d","occurred_at":"2020-12-12T03:59:56Z","subj_id":"https:\/\/en.wikipedia.org\/api\/rest_v1\/page\/html\/Enactivism\/993725797","id":"a9cd3f57-040b-43e2-a5f1-25bed8abc03d","evidence_record":"https:\/\/evidence.eventdata.crossref.org\/evidence\/20201212-wikipedia-1df48be3-cde5-4fbc-89d0-1025d7d1525d","terms":"https:\/\/doi.org\/10.13003\/CED-terms-of-use","action":"add","subj":{"pid":"https:\/\/en.wikipedia.org\/wiki\/Enactivism","url":"https:\/\/en.wikipedia.org\/w\/index.php?title=Enactivism&oldid=993725797","title":"Enactivism","work_type_id":"entry-encyclopedia","api-url":"https:\/\/en.wikipedia.org\/api\/rest_v1\/page\/html\/Enactivism\/993725797"},"source_id":"wikipedia","obj":{"pid":"https:\/\/doi.org\/10.1177\/1354067x9952006","url":"https:\/\/doi.org\/10.1177\/1354067x9952006","method":"doi-literal","verification":"literal"},"timestamp":"2020-12-12T04:05:32Z","relation_type_id":"references"},{"license":"https:\/\/creativecommons.org\/publicdomain\/zero\/1.0\/","obj_id":"https:\/\/doi.org\/10.1177\/1354067x9952006","source_token":"36c35e23-8757-4a9d-aacf-345e9b7eb50d","occurred_at":"2020-12-12T06:12:44Z","subj_id":"https:\/\/en.wikipedia.org\/api\/rest_v1\/page\/html\/Enactivism\/993740295","id":"a6afa11d-54ed-42c6-8269-046d0a77f46e","evidence_record":"https:\/\/evidence.eventdata.crossref.org\/evidence\/20201212-wikipedia-5758125d-235c-4040-a6f2-690babba7bd4","terms":"https:\/\/doi.org\/10.13003\/CED-terms-of-use","action":"add","subj":{"pid":"https:\/\/en.wikipedia.org\/wiki\/Enactivism","url":"https:\/\/en.wikipedia.org\/w\/index.php?title=Enactivism&oldid=993740295","title":"Enactivism","work_type_id":"entry-encyclopedia","api-url":"https:\/\/en.wikipedia.org\/api\/rest_v1\/page\/html\/Enactivism\/993740295"},"source_id":"wikipedia","obj":{"pid":"https:\/\/doi.org\/10.1177\/1354067x9952006","url":"https:\/\/doi.org\/10.1177\/1354067x9952006","method":"doi-literal","verification":"literal"},"timestamp":"2020-12-12T06:19:27Z","relation_type_id":"references"},{"license":"https:\/\/creativecommons.org\/publicdomain\/zero\/1.0\/","obj_id":"https:\/\/doi.org\/10.1177\/1354067x9952006","source_token":"36c35e23-8757-4a9d-aacf-345e9b7eb50d","occurred_at":"2020-12-12T06:20:48Z","subj_id":"https:\/\/en.wikipedia.org\/api\/rest_v1\/page\/html\/Enactivism\/993741054","id":"71290771-6852-4f8c-a40b-e7108754728c","evidence_record":"https:\/\/evidence.eventdata.crossref.org\/evidence\/20201212-wikipedia-3bf81a0b-52cf-457c-ae62-70941196532c","terms":"https:\/\/doi.org\/10.13003\/CED-terms-of-use","action":"add","subj":{"pid":"https:\/\/en.wikipedia.org\/wiki\/Enactivism","url":"https:\/\/en.wikipedia.org\/w\/index.php?title=Enactivism&oldid=993741054","title":"Enactivism","work_type_id":"entry-encyclopedia","api-url":"https:\/\/en.wikipedia.org\/api\/rest_v1\/page\/html\/Enactivism\/993741054"},"source_id":"wikipedia","obj":{"pid":"https:\/\/doi.org\/10.1177\/1354067x9952006","url":"https:\/\/doi.org\/10.1177\/1354067x9952006","method":"doi-literal","verification":"literal"},"timestamp":"2020-12-12T06:35:36Z","relation_type_id":"references"},{"license":"https:\/\/creativecommons.org\/publicdomain\/zero\/1.0\/","obj_id":"https:\/\/doi.org\/10.1177\/1354067x9952006","source_token":"36c35e23-8757-4a9d-aacf-345e9b7eb50d","occurred_at":"2020-12-12T06:43:34Z","subj_id":"https:\/\/en.wikipedia.org\/api\/rest_v1\/page\/html\/Enactivism\/993743475","id":"cbbc4818-2acf-48f1-ac52-c7e44064fbda","evidence_record":"https:\/\/evidence.eventdata.crossref.org\/evidence\/20201212-wikipedia-685f4b2d-c5bb-4ca4-a334-63f617ea8fb3","terms":"https:\/\/doi.org\/10.13003\/CED-terms-of-use","action":"add","subj":{"pid":"https:\/\/en.wikipedia.org\/wiki\/Enactivism","url":"https:\/\/en.wikipedia.org\/w\/index.php?title=Enactivism&oldid=993743475","title":"Enactivism","work_type_id":"entry-encyclopedia","api-url":"https:\/\/en.wikipedia.org\/api\/rest_v1\/page\/html\/Enactivism\/993743475"},"source_id":"wikipedia","obj":{"pid":"https:\/\/doi.org\/10.1177\/1354067x9952006","url":"https:\/\/doi.org\/10.1177\/1354067x9952006","method":"doi-literal","verification":"literal"},"timestamp":"2020-12-12T07:01:36Z","relation_type_id":"references"},{"license":"https:\/\/creativecommons.org\/publicdomain\/zero\/1.0\/","obj_id":"https:\/\/doi.org\/10.1177\/1354067x9952006","source_token":"36c35e23-8757-4a9d-aacf-345e9b7eb50d","occurred_at":"2020-12-12T06:49:07Z","subj_id":"https:\/\/en.wikipedia.org\/api\/rest_v1\/page\/html\/Enactivism\/993744047","id":"04a804ec-1dac-4fe4-96c1-346a59838671","evidence_record":"https:\/\/evidence.eventdata.crossref.org\/evidence\/20201212-wikipedia-7a8ec023-ef51-43fb-883a-6ba82505258e","terms":"https:\/\/doi.org\/10.13003\/CED-terms-of-use","action":"add","subj":{"pid":"https:\/\/en.wikipedia.org\/wiki\/Enactivism","url":"https:\/\/en.wikipedia.org\/w\/index.php?title=Enactivism&oldid=993744047","title":"Enactivism","work_type_id":"entry-encyclopedia","api-url":"https:\/\/en.wikipedia.org\/api\/rest_v1\/page\/html\/Enactivism\/993744047"},"source_id":"wikipedia","obj":{"pid":"https:\/\/doi.org\/10.1177\/1354067x9952006","url":"https:\/\/doi.org\/10.1177\/1354067x9952006","method":"doi-literal","verification":"literal"},"timestamp":"2020-12-12T07:07:50Z","relation_type_id":"references"},{"license":"https:\/\/creativecommons.org\/publicdomain\/zero\/1.0\/","obj_id":"https:\/\/doi.org\/10.1177\/1354067x9952006","source_token":"36c35e23-8757-4a9d-aacf-345e9b7eb50d","occurred_at":"2020-12-12T12:43:14Z","subj_id":"https:\/\/en.wikipedia.org\/api\/rest_v1\/page\/html\/Enactivism\/993775347","id":"3f3f6c3c-06fb-49dc-beff-ade2bbc07344","evidence_record":"https:\/\/evidence.eventdata.crossref.org\/evidence\/20201212-wikipedia-a2d204c3-faf4-4ef9-b19c-7d9c72aadf3b","terms":"https:\/\/doi.org\/10.13003\/CED-terms-of-use","action":"add","subj":{"pid":"https:\/\/en.wikipedia.org\/wiki\/Enactivism","url":"https:\/\/en.wikipedia.org\/w\/index.php?title=Enactivism&oldid=993775347","title":"Enactivism","work_type_id":"entry-encyclopedia","api-url":"https:\/\/en.wikipedia.org\/api\/rest_v1\/page\/html\/Enactivism\/993775347"},"source_id":"wikipedia","obj":{"pid":"https:\/\/doi.org\/10.1177\/1354067x9952006","url":"https:\/\/doi.org\/10.1177\/1354067x9952006","method":"doi-literal","verification":"literal"},"timestamp":"2020-12-12T12:50:44Z","relation_type_id":"references"},{"license":"https:\/\/creativecommons.org\/publicdomain\/zero\/1.0\/","obj_id":"https:\/\/doi.org\/10.1177\/1354067x9952006","source_token":"36c35e23-8757-4a9d-aacf-345e9b7eb50d","occurred_at":"2020-12-22T17:12:42Z","subj_id":"https:\/\/en.wikipedia.org\/api\/rest_v1\/page\/html\/Enactivism\/995740514","id":"0c6a2be1-8596-452b-a3b2-2360fc916e0a","evidence_record":"https:\/\/evidence.eventdata.crossref.org\/evidence\/20201222-wikipedia-2f3c22e5-14c6-4c79-8e69-a7f949e93337","terms":"https:\/\/doi.org\/10.13003\/CED-terms-of-use","action":"add","subj":{"pid":"https:\/\/en.wikipedia.org\/wiki\/Enactivism","url":"https:\/\/en.wikipedia.org\/w\/index.php?title=Enactivism&oldid=995740514","title":"Enactivism","work_type_id":"entry-encyclopedia","api-url":"https:\/\/en.wikipedia.org\/api\/rest_v1\/page\/html\/Enactivism\/995740514"},"source_id":"wikipedia","obj":{"pid":"https:\/\/doi.org\/10.1177\/1354067x9952006","url":"https:\/\/doi.org\/10.1177\/1354067x9952006","method":"doi-literal","verification":"literal"},"timestamp":"2020-12-22T17:32:13Z","relation_type_id":"references"},{"license":"https:\/\/creativecommons.org\/publicdomain\/zero\/1.0\/","obj_id":"https:\/\/doi.org\/10.1177\/1354067x9952006","source_token":"36c35e23-8757-4a9d-aacf-345e9b7eb50d","occurred_at":"2020-12-22T17:28:44Z","subj_id":"https:\/\/en.wikipedia.org\/api\/rest_v1\/page\/html\/Enactivism\/995742930","id":"b875e0e4-4297-45be-b228-fa74131b5a0c","evidence_record":"https:\/\/evidence.eventdata.crossref.org\/evidence\/20201222-wikipedia-c9084e67-73b5-4ad3-8969-744e8d47ec9a","terms":"https:\/\/doi.org\/10.13003\/CED-terms-of-use","action":"add","subj":{"pid":"https:\/\/en.wikipedia.org\/wiki\/Enactivism","url":"https:\/\/en.wikipedia.org\/w\/index.php?title=Enactivism&oldid=995742930","title":"Enactivism","work_type_id":"entry-encyclopedia","api-url":"https:\/\/en.wikipedia.org\/api\/rest_v1\/page\/html\/Enactivism\/995742930"},"source_id":"wikipedia","obj":{"pid":"https:\/\/doi.org\/10.1177\/1354067x9952006","url":"https:\/\/doi.org\/10.1177\/1354067x9952006","method":"doi-literal","verification":"literal"},"timestamp":"2020-12-22T17:39:37Z","relation_type_id":"references"},{"license":"https:\/\/creativecommons.org\/publicdomain\/zero\/1.0\/","obj_id":"https:\/\/doi.org\/10.1177\/1354067x9952006","source_token":"36c35e23-8757-4a9d-aacf-345e9b7eb50d","occurred_at":"2021-01-07T19:40:42Z","subj_id":"https:\/\/en.wikipedia.org\/api\/rest_v1\/page\/html\/Enactivism\/998947605","id":"6d1a038c-a83e-400f-beaa-29d564013b7f","evidence_record":"https:\/\/evidence.eventdata.crossref.org\/evidence\/20210107-wikipedia-83a3ea1a-37c2-4548-9408-b82ab689711c","terms":"https:\/\/doi.org\/10.13003\/CED-terms-of-use","action":"add","subj":{"pid":"https:\/\/en.wikipedia.org\/wiki\/Enactivism","url":"https:\/\/en.wikipedia.org\/w\/index.php?title=Enactivism&oldid=998947605","title":"Enactivism","work_type_id":"entry-encyclopedia","api-url":"https:\/\/en.wikipedia.org\/api\/rest_v1\/page\/html\/Enactivism\/998947605"},"source_id":"wikipedia","obj":{"pid":"https:\/\/doi.org\/10.1177\/1354067x9952006","url":"https:\/\/doi.org\/10.1177\/1354067x9952006","method":"doi-literal","verification":"literal"},"timestamp":"2021-01-07T19:49:02Z","relation_type_id":"references"},{"license":"https:\/\/creativecommons.org\/publicdomain\/zero\/1.0\/","obj_id":"https:\/\/doi.org\/10.1177\/1354067x9952006","source_token":"36c35e23-8757-4a9d-aacf-345e9b7eb50d","occurred_at":"2021-01-07T19:46:25Z","subj_id":"https:\/\/en.wikipedia.org\/api\/rest_v1\/page\/html\/Enactivism\/998948536","id":"c8375dca-c9c0-4100-9e43-cd14b8d7d9f0","evidence_record":"https:\/\/evidence.eventdata.crossref.org\/evidence\/20210107-wikipedia-615a834c-be4a-4f61-95d6-fec37ad8342c","terms":"https:\/\/doi.org\/10.13003\/CED-terms-of-use","action":"add","subj":{"pid":"https:\/\/en.wikipedia.org\/wiki\/Enactivism","url":"https:\/\/en.wikipedia.org\/w\/index.php?title=Enactivism&oldid=998948536","title":"Enactivism","work_type_id":"entry-encyclopedia","api-url":"https:\/\/en.wikipedia.org\/api\/rest_v1\/page\/html\/Enactivism\/998948536"},"source_id":"wikipedia","obj":{"pid":"https:\/\/doi.org\/10.1177\/1354067x9952006","url":"https:\/\/doi.org\/10.1177\/1354067x9952006","method":"doi-literal","verification":"literal"},"timestamp":"2021-01-07T19:57:13Z","relation_type_id":"references"},{"license":"https:\/\/creativecommons.org\/publicdomain\/zero\/1.0\/","obj_id":"https:\/\/doi.org\/10.1177\/1354067x9952006","source_token":"36c35e23-8757-4a9d-aacf-345e9b7eb50d","occurred_at":"2021-01-08T12:27:35Z","subj_id":"https:\/\/en.wikipedia.org\/api\/rest_v1\/page\/html\/Enactivism\/999088073","id":"26e1e52e-02c1-4f2a-a56d-48a2300f389d","evidence_record":"https:\/\/evidence.eventdata.crossref.org\/evidence\/20210108-wikipedia-118b5c9d-334c-4df6-a560-85264deaacc5","terms":"https:\/\/doi.org\/10.13003\/CED-terms-of-use","action":"add","subj":{"pid":"https:\/\/en.wikipedia.org\/wiki\/Enactivism","url":"https:\/\/en.wikipedia.org\/w\/index.php?title=Enactivism&oldid=999088073","title":"Enactivism","work_type_id":"entry-encyclopedia","api-url":"https:\/\/en.wikipedia.org\/api\/rest_v1\/page\/html\/Enactivism\/999088073"},"source_id":"wikipedia","obj":{"pid":"https:\/\/doi.org\/10.1177\/1354067x9952006","url":"https:\/\/doi.org\/10.1177\/1354067x9952006","method":"doi-literal","verification":"literal"},"timestamp":"2021-01-08T12:51:48Z","relation_type_id":"references"},{"license":"https:\/\/creativecommons.org\/publicdomain\/zero\/1.0\/","obj_id":"https:\/\/doi.org\/10.1177\/1354067x9952006","source_token":"36c35e23-8757-4a9d-aacf-345e9b7eb50d","occurred_at":"2021-01-14T02:55:57Z","subj_id":"https:\/\/en.wikipedia.org\/api\/rest_v1\/page\/html\/Enactivism\/1000204129","id":"60406fcb-2b9a-4949-8a15-0da90b05a475","evidence_record":"https:\/\/evidence.eventdata.crossref.org\/evidence\/20210114-wikipedia-4a085877-9650-4edb-8f1e-5f0ded5bb57e","terms":"https:\/\/doi.org\/10.13003\/CED-terms-of-use","action":"add","subj":{"pid":"https:\/\/en.wikipedia.org\/wiki\/Enactivism","url":"https:\/\/en.wikipedia.org\/w\/index.php?title=Enactivism&oldid=1000204129","title":"Enactivism","work_type_id":"entry-encyclopedia","api-url":"https:\/\/en.wikipedia.org\/api\/rest_v1\/page\/html\/Enactivism\/1000204129"},"source_id":"wikipedia","obj":{"pid":"https:\/\/doi.org\/10.1177\/1354067x9952006","url":"https:\/\/doi.org\/10.1177\/1354067x9952006","method":"doi-literal","verification":"literal"},"timestamp":"2021-01-14T03:08:12Z","relation_type_id":"references"},{"license":"https:\/\/creativecommons.org\/publicdomain\/zero\/1.0\/","obj_id":"https:\/\/doi.org\/10.1177\/1354067x9952006","source_token":"36c35e23-8757-4a9d-aacf-345e9b7eb50d","occurred_at":"2021-01-14T07:45:45Z","subj_id":"https:\/\/en.wikipedia.org\/api\/rest_v1\/page\/html\/Enactivism\/1000239497","id":"7a1944fa-5a09-4743-8346-0c379c59e088","evidence_record":"https:\/\/evidence.eventdata.crossref.org\/evidence\/20210114-wikipedia-7dd4dd9b-405e-446f-941f-cfa9c1f8259f","terms":"https:\/\/doi.org\/10.13003\/CED-terms-of-use","action":"add","subj":{"pid":"https:\/\/en.wikipedia.org\/wiki\/Enactivism","url":"https:\/\/en.wikipedia.org\/w\/index.php?title=Enactivism&oldid=1000239497","title":"Enactivism","work_type_id":"entry-encyclopedia","api-url":"https:\/\/en.wikipedia.org\/api\/rest_v1\/page\/html\/Enactivism\/1000239497"},"source_id":"wikipedia","obj":{"pid":"https:\/\/doi.org\/10.1177\/1354067x9952006","url":"https:\/\/doi.org\/10.1177\/1354067x9952006","method":"doi-literal","verification":"literal"},"timestamp":"2021-01-14T07:52:05Z","relation_type_id":"references"},{"license":"https:\/\/creativecommons.org\/publicdomain\/zero\/1.0\/","obj_id":"https:\/\/doi.org\/10.1177\/1354067x9952006","source_token":"36c35e23-8757-4a9d-aacf-345e9b7eb50d","occurred_at":"2021-02-06T01:11:18Z","subj_id":"https:\/\/en.wikipedia.org\/api\/rest_v1\/page\/html\/Enactivism\/1005109360","id":"954901f6-9569-4144-9886-8a66e9a0df23","evidence_record":"https:\/\/evidence.eventdata.crossref.org\/evidence\/20210206-wikipedia-6f8a28e9-bd56-4868-819c-0215c9d14856","terms":"https:\/\/doi.org\/10.13003\/CED-terms-of-use","action":"add","subj":{"pid":"https:\/\/en.wikipedia.org\/wiki\/Enactivism","url":"https:\/\/en.wikipedia.org\/w\/index.php?title=Enactivism&oldid=1005109360","title":"Enactivism","work_type_id":"entry-encyclopedia","api-url":"https:\/\/en.wikipedia.org\/api\/rest_v1\/page\/html\/Enactivism\/1005109360"},"source_id":"wikipedia","obj":{"pid":"https:\/\/doi.org\/10.1177\/1354067x9952006","url":"https:\/\/doi.org\/10.1177\/1354067x9952006","method":"doi-literal","verification":"literal"},"timestamp":"2021-02-06T01:18:21Z","relation_type_id":"references"},{"license":"https:\/\/creativecommons.org\/publicdomain\/zero\/1.0\/","obj_id":"https:\/\/doi.org\/10.1177\/1354067x9952006","source_token":"36c35e23-8757-4a9d-aacf-345e9b7eb50d","occurred_at":"2021-02-16T16:08:49Z","subj_id":"https:\/\/en.wikipedia.org\/api\/rest_v1\/page\/html\/Enactivism\/1007126356","id":"e8bf3158-02b7-4830-8147-b53a24190c7d","evidence_record":"https:\/\/evidence.eventdata.crossref.org\/evidence\/20210216-wikipedia-b9ef79b3-7967-43a1-adf3-7a5df89d2c91","terms":"https:\/\/doi.org\/10.13003\/CED-terms-of-use","action":"add","subj":{"pid":"https:\/\/en.wikipedia.org\/wiki\/Enactivism","url":"https:\/\/en.wikipedia.org\/w\/index.php?title=Enactivism&oldid=1007126356","title":"Enactivism","work_type_id":"entry-encyclopedia","api-url":"https:\/\/en.wikipedia.org\/api\/rest_v1\/page\/html\/Enactivism\/1007126356"},"source_id":"wikipedia","obj":{"pid":"https:\/\/doi.org\/10.1177\/1354067x9952006","url":"https:\/\/doi.org\/10.1177\/1354067x9952006","method":"doi-literal","verification":"literal"},"timestamp":"2021-02-16T16:45:48Z","relation_type_id":"references"}]}}