{"status":"ok","message-type":"event-list","message":{"next-cursor":"747c674c-1de3-44ee-b865-99a614845836","total-results":5,"items-per-page":1000,"events":[{"license":"https:\/\/creativecommons.org\/publicdomain\/zero\/1.0\/","obj_id":"https:\/\/doi.org\/10.1080\/00049189808703224","source_token":"45a1ef76-4f43-4cdc-9ba8-5a6ad01cc231","occurred_at":"2017-08-22T05:00:01Z","subj_id":"http:\/\/twitter.com\/austgeog\/statuses\/899858676361551872","id":"412b0aab-1a17-4411-a27f-ba197c67d2a4","evidence_record":"https:\/\/evidence.eventdata.crossref.org\/evidence\/20170822-twitter-9f19f4c3-b959-49d3-a595-fed38066a19d","terms":"https:\/\/doi.org\/10.13003\/CED-terms-of-use","action":"add","subj":{"pid":"http:\/\/twitter.com\/austgeog\/statuses\/899858676361551872","title":"Tweet 899858676361551872","issued":"2017-08-22T05:00:01.000Z","author":{"url":"http:\/\/www.twitter.com\/austgeog"},"original-tweet-url":"http:\/\/twitter.com\/austgeog\/statuses\/899858676361551872","original-tweet-author":null,"alternative-id":"899858676361551872"},"source_id":"twitter","obj":{"pid":"https:\/\/doi.org\/10.1080\/00049189808703224","url":"http:\/\/www.tandfonline.com\/doi\/abs\/10.1080\/00049189808703224"},"timestamp":"2017-08-22T05:00:22Z","relation_type_id":"discusses"},{"license":"https:\/\/creativecommons.org\/publicdomain\/zero\/1.0\/","obj_id":"https:\/\/doi.org\/10.1080\/00049189808703224","source_token":"45a1ef76-4f43-4cdc-9ba8-5a6ad01cc231","occurred_at":"2017-08-22T05:26:49Z","subj_id":"http:\/\/twitter.com\/RobynSydney\/statuses\/899865420072484864","id":"84a38a66-aaf1-482f-92b4-ef132420dbe2","evidence_record":"https:\/\/evidence.eventdata.crossref.org\/evidence\/20170822-twitter-8a40bca3-ea72-4f80-87ed-891fdc0f5172","terms":"https:\/\/doi.org\/10.13003\/CED-terms-of-use","action":"add","subj":{"pid":"http:\/\/twitter.com\/RobynSydney\/statuses\/899865420072484864","title":"Tweet 899865420072484864","issued":"2017-08-22T05:26:49.000Z","author":{"url":"http:\/\/www.twitter.com\/RobynSydney"},"original-tweet-url":"http:\/\/twitter.com\/RobynSydney\/statuses\/899865420072484864","original-tweet-author":null,"alternative-id":"899865420072484864"},"source_id":"twitter","obj":{"pid":"https:\/\/doi.org\/10.1080\/00049189808703224","url":"http:\/\/www.tandfonline.com\/doi\/abs\/10.1080\/00049189808703224"},"timestamp":"2017-08-22T05:28:06Z","relation_type_id":"discusses"},{"license":"https:\/\/creativecommons.org\/publicdomain\/zero\/1.0\/","obj_id":"https:\/\/doi.org\/10.1080\/00049189808703224","source_token":"45a1ef76-4f43-4cdc-9ba8-5a6ad01cc231","occurred_at":"2017-08-22T06:50:02Z","subj_id":"http:\/\/twitter.com\/AUSCCER\/statuses\/899886361187987457","id":"ec1b8309-32a7-48b6-b9cb-a1f067b4f80d","evidence_record":"https:\/\/evidence.eventdata.crossref.org\/evidence\/20170822-twitter-f3e0f35f-7a27-47a3-b5b8-e052c6ea373b","terms":"https:\/\/doi.org\/10.13003\/CED-terms-of-use","action":"add","subj":{"pid":"http:\/\/twitter.com\/AUSCCER\/statuses\/899886361187987457","title":"Tweet 899886361187987457","issued":"2017-08-22T06:50:02.000Z","author":{"url":"http:\/\/www.twitter.com\/AUSCCER"},"original-tweet-url":"http:\/\/twitter.com\/austgeog\/statuses\/899858676361551872","original-tweet-author":"http:\/\/www.twitter.com\/austgeog","alternative-id":"899886361187987457"},"source_id":"twitter","obj":{"pid":"https:\/\/doi.org\/10.1080\/00049189808703224","url":"http:\/\/www.tandfonline.com\/doi\/abs\/10.1080\/00049189808703224"},"timestamp":"2017-08-22T06:50:34Z","relation_type_id":"discusses"},{"license":"https:\/\/creativecommons.org\/publicdomain\/zero\/1.0\/","obj_id":"https:\/\/doi.org\/10.1080\/00049189808703224","source_token":"45a1ef76-4f43-4cdc-9ba8-5a6ad01cc231","occurred_at":"2017-08-22T10:45:26Z","subj_id":"http:\/\/twitter.com\/CrystalLegacy1\/statuses\/899945601877458945","id":"5dc97844-7259-48fe-a231-ee0774b1dadb","evidence_record":"https:\/\/evidence.eventdata.crossref.org\/evidence\/20170822-twitter-f47ad33b-c87a-4a19-a1e0-e0ebc0e6bc9f","terms":"https:\/\/doi.org\/10.13003\/CED-terms-of-use","action":"add","subj":{"pid":"http:\/\/twitter.com\/CrystalLegacy1\/statuses\/899945601877458945","title":"Tweet 899945601877458945","issued":"2017-08-22T10:45:26.000Z","author":{"url":"http:\/\/www.twitter.com\/CrystalLegacy1"},"original-tweet-url":"http:\/\/twitter.com\/austgeog\/statuses\/899858676361551872","original-tweet-author":"http:\/\/www.twitter.com\/austgeog","alternative-id":"899945601877458945"},"source_id":"twitter","obj":{"pid":"https:\/\/doi.org\/10.1080\/00049189808703224","url":"http:\/\/www.tandfonline.com\/doi\/abs\/10.1080\/00049189808703224"},"timestamp":"2017-08-22T10:46:01Z","relation_type_id":"discusses"},{"license":"https:\/\/creativecommons.org\/publicdomain\/zero\/1.0\/","obj_id":"https:\/\/doi.org\/10.1080\/00049189808703224","source_token":"45a1ef76-4f43-4cdc-9ba8-5a6ad01cc231","occurred_at":"2017-08-26T07:06:41Z","subj_id":"http:\/\/twitter.com\/UrbanSSAP\/statuses\/901340103284371456","id":"747c674c-1de3-44ee-b865-99a614845836","evidence_record":"https:\/\/evidence.eventdata.crossref.org\/evidence\/20170826-twitter-7c19dacb-e385-4b4a-bbfa-072de1e4b7f7","terms":"https:\/\/doi.org\/10.13003\/CED-terms-of-use","action":"add","subj":{"pid":"http:\/\/twitter.com\/UrbanSSAP\/statuses\/901340103284371456","title":"Tweet 901340103284371456","issued":"2017-08-26T07:06:41.000Z","author":{"url":"http:\/\/www.twitter.com\/UrbanSSAP"},"original-tweet-url":"http:\/\/twitter.com\/austgeog\/statuses\/899858676361551872","original-tweet-author":"http:\/\/www.twitter.com\/austgeog","alternative-id":"901340103284371456"},"source_id":"twitter","obj":{"pid":"https:\/\/doi.org\/10.1080\/00049189808703224","url":"http:\/\/www.tandfonline.com\/doi\/abs\/10.1080\/00049189808703224"},"timestamp":"2017-08-26T07:07:50Z","relation_type_id":"discusses"}]}}