{"status":"ok","message-type":"event-list","message":{"next-cursor":"8b53179b-9194-43b3-a2fe-e63ebf8964e5","total-results":5,"items-per-page":1000,"events":[{"license":"https:\/\/doi.org\/10.13003\/CED-terms-of-use","obj_id":"https:\/\/doi.org\/10.1086\/514309","source_token":"8676e950-8ac5-4074-8ac3-c0a18ada7e99","occurred_at":"2011-11-01T00:00:00Z","subj_id":"https:\/\/doi.org\/10.1093\/infdis\/jir344","id":"df543619-f9bc-4d07-af9a-4359b57641a0","terms":"https:\/\/doi.org\/10.13003\/CED-terms-of-use","message_action":"create","source_id":"crossref","timestamp":"2019-07-03T22:13:25Z","relation_type_id":"references"},{"license":"https:\/\/doi.org\/10.13003\/CED-terms-of-use","obj_id":"https:\/\/doi.org\/10.1086\/514309","source_token":"8676e950-8ac5-4074-8ac3-c0a18ada7e99","occurred_at":"2017-01-31T00:00:00Z","subj_id":"https:\/\/doi.org\/10.1038\/sdata.2016.133","id":"6a2be17e-835d-4a2a-99d3-452e16ed533d","terms":"https:\/\/doi.org\/10.13003\/CED-terms-of-use","message_action":"create","source_id":"crossref","timestamp":"2019-07-18T08:12:58Z","relation_type_id":"references"},{"license":"https:\/\/doi.org\/10.13003\/CED-terms-of-use","obj_id":"https:\/\/doi.org\/10.1086\/514309","source_token":"8676e950-8ac5-4074-8ac3-c0a18ada7e99","occurred_at":"2017-04-10T00:00:00Z","subj_id":"https:\/\/doi.org\/10.1098\/rstb.2016.0303","id":"f2172b5e-d820-49c0-beb2-1645a66b85d1","terms":"https:\/\/doi.org\/10.13003\/CED-terms-of-use","message_action":"create","source_id":"crossref","timestamp":"2019-07-20T15:22:39Z","relation_type_id":"references"},{"license":"https:\/\/doi.org\/10.13003\/CED-terms-of-use","obj_id":"https:\/\/doi.org\/10.1086\/514309","source_token":"8676e950-8ac5-4074-8ac3-c0a18ada7e99","occurred_at":"2018-06-18T00:00:00Z","subj_id":"https:\/\/doi.org\/10.1093\/infdis\/jiy251","id":"2fba7427-b713-4557-8274-032609d9e3b6","terms":"https:\/\/doi.org\/10.13003\/CED-terms-of-use","message_action":"create","source_id":"crossref","timestamp":"2019-12-04T07:18:42Z","relation_type_id":"references"},{"license":"https:\/\/doi.org\/10.13003\/CED-terms-of-use","obj_id":"https:\/\/doi.org\/10.1086\/514309","source_token":"8676e950-8ac5-4074-8ac3-c0a18ada7e99","occurred_at":"2012-06-26T00:00:00Z","subj_id":"https:\/\/doi.org\/10.1371\/journal.pntd.0001546","id":"8b53179b-9194-43b3-a2fe-e63ebf8964e5","terms":"https:\/\/doi.org\/10.13003\/CED-terms-of-use","message_action":"create","source_id":"crossref","timestamp":"2019-12-09T21:20:34Z","relation_type_id":"references"}]}}